Workbook
Name M.CD: Main!$R$5
Name M.UC: Main!$R$4
Name P.CD: Main!$N$5
Name P.UC: Main!$N$4
Name TR: Sheet2!$AE$31

Sheet Main
B3: Name | C3: Platform | D3: Type | E3: Phase | F3: Finish | G3: Price | I3: Patient Pool | J3: US | K3: EU5 | L3: Japan | N3: Peak Market | O3: Ramp up | Q3: Growth | R3: Mortality
B4: Obefazimod (ABX464) | C4: Monotherapy | D4: UC | E4: III | F4: 2025 | G4: 50000 | I4: =+SUM(J4:L4) -> 387000 | J4: =(135000+240000)/2 -> 187500 | K4: =(112500+216000)/2 -> 164250 | L4: =(22500+48000)/2 -> 35250 | N4: 0.05 | O4: 5 to 7 years | Q4: 22500 | R4: 0.00753
B5: Obefazimod (ABX464) | C5: Monotherapy | D5: CD | E5: Iib | F5: 2027 | G5: 50000 | I5: =+SUM(J5:L5) -> 311100 | J5: =(105000+192000)/2 -> 148500 | K5: =(90000+192000)/2 -> 141000 | L5: =(12000+31200)/2 -> 21600 | N5: 0.05 | O5: 5 to 7 years | Q5: 15000 | R5: 0.00753
B8: Competitors
B9: Biologics: Remicade (infliximab), Humira (adalimumab), Entyvio (vedolizumab), Cimzia
B10: Oral therapies: Xeljanz (tofacitinib), Rinvoq (upadacitinib), Zeposia (ozanimod)
B12: Market | J12: Cash | K12: 222300
B13: Therapy | C13: UC | D13: CD | E13: Producer | J13: Debt | K13: 119600
B14: Humira (Adalimumab) | C14: 0.15 | D14: 0.2 | E14: AbbVie | G14: =+SUM(C14:C18)+C21 -> 0.65 | J14: Mrkt Cap | K14: 541800
B15: Remicade (Infliximab) | C15: 0.1 | D15: 0.12 | E15: J&J | G15: =1-G14 -> 0.35 | J15: EV | K15: =+K14-K12+K13 -> 439100
B16: Entyvio (Vedolizumab) | C16: 0.15 | D16: 0.15 | E16: Takeda | J16: Shares | K16: 42547.568
B17: Stelara (Ustekinumab) | C17: 0.1 | D17: 0.12 | E17: J&J
B18: Skyrizi (Risankizumab) | C18: 0.05 | D18: 0.1 | E18: AbbVie
B19: Xeljanz (Tofacitinib) | C19: 0.08 | D19: 0.05 | E19: Pfizer
B20: Zeposia (Ozanimod) | C20: 0.05 | D20: 0.03 | E20: BMS
B21: Biosimilars | C21: 0.1 | D21: 0.1
B22: Other Therapies | C22: 0.22 | D22: 0.13

Sheet Sheet2
L2: 2024 | M2: =+L2+1 -> 2025 | N2: =+M2+1 -> 2026 | O2: =+N2+1 -> 2027 | P2: =+O2+1 -> 2028 | Q2: =+P2+1 -> 2029 | R2: =+Q2+1 -> 2030 | S2: =+R2+1 -> 2031 | T2: =+S2+1 -> 2032 | ... BF2: =+BE2+1 -> 2070
B4: UC
B5: Patients | L5: =+Main!I4 -> 387000 | M5: =+L5+L6-L7 -> 406585.89 | N5: =+M5+M6-M7 -> 426024.3 | O5: =+N5+N6-N7 -> 445316.34 | P5: =+O5+O6-O7 -> 464463.1 | Q5: =+P5+P6-P7 -> 483465.7 | R5: =+Q5+Q6-Q7 -> 502325.2 | S5: =+R5+R6-R7 -> 521042.69 | T5: =+S5+S6-S7 -> 539619.24 | ... W5: =+V5+V6-V7 -> 594513.8
B6: New Patients | L6: =+Main!Q4 -> 22500 | M6: =+L6 -> 22500 | N6: =+M6 -> 22500 | O6: =+N6 -> 22500 | P6: =+O6 -> 22500 | Q6: =+P6 -> 22500 | R6: =+Q6 -> 22500 | S6: =+R6 -> 22500 | T6: =+S6 -> 22500 | ... W6: =+V6 -> 22500
B7: Died | L7: =+L5*M.UC -> 2914.11 | M7: =+M5*M.UC -> 3061.5918 | N7: =+N5*M.UC -> 3207.963 | O7: =+O5*M.UC -> 3353.232 | P7: =+P5*M.UC -> 3497.4072 | Q7: =+Q5*M.UC -> 3640.4967 | R7: =+R5*M.UC -> 3782.5088 | S7: =+S5*M.UC -> 3923.4515 | ... W7: =+W5*M.UC -> 4476.6889
B9: CD
B10: Patients | L10: =+Main!I5 -> 311100 | M10: =+L10+L11-L12 -> 323757.42 | N10: =+M10+M11-M12 -> 336319.52 | O10: =+N10+N11-N12 -> 348787.04 | P10: =+O10+O11-O12 -> 361160.67 | Q10: =+P10+P11-P12 -> 373441.13 | R10: =+Q10+Q11-Q12 -> 385629.12 | S10: =+R10+R11-R12 -> 397725.33 | T10: =+S10+S11-S12 -> 409730.46 | ... W10: =+V10+V11-V12 -> 445206.17
B11: New Patients | L11: =+Main!Q5 -> 15000 | M11: =+L11 -> 15000 | N11: =+M11 -> 15000 | O11: =+N11 -> 15000 | P11: =+O11 -> 15000 | Q11: =+P11 -> 15000 | R11: =+Q11 -> 15000 | S11: =+R11 -> 15000 | T11: =+S11 -> 15000 | ... W11: =+V11 -> 15000
B12: Died | L12: =+L10*M.CD -> 2342.583 | M12: =+M10*M.CD -> 2437.8934 | N12: =+N10*M.CD -> 2532.486 | O12: =+O10*M.CD -> 2626.3664 | P12: =+P10*M.CD -> 2719.5399 | Q12: =+Q10*M.CD -> 2812.0117 | R12: =+R10*M.CD -> 2903.7873 | S12: =+S10*M.CD -> 2994.8718 | ... W12: =+W10*M.CD -> 3352.4025
B14: ABX464 UC Patients | M14: Approved | O14: =+T14*0.1 -> 2698.0962 | P14: =+T14*0.3 -> 8094.2886 | Q14: =+T14*0.5 -> 13490.481 | R14: =+T14*0.7 -> 18886.673 | S14: =+T14*0.85 -> 22933.818 | T14: =+T5*P.UC -> 26980.962 | U14: =+U5*P.UC -> 27902.795 | V14: =+V5*P.UC -> 28817.687 | W14: =+W5*P.UC -> 29725.69
B15: ABX464 CD Patients | N15: Approved | P15: =+U15*0.1 -> 2108.226 | Q15: =+U15*0.3 -> 6324.6779 | R15: =+U15*0.5 -> 10541.13 | S15: =+U15*0.7 -> 14757.582 | T15: =+U15*0.85 -> 17919.921 | U15: =+U10*P.CD -> 21082.26 | V15: =+V10*P.CD -> 21673.51 | W15: =+W10*P.CD -> 22260.309
B16: ABX464 Price | M16: 35 | N16: 35 | O16: 35 | P16: 35 | Q16: 35 | R16: 35 | S16: 35 | T16: 35 | U16: 35 | V16: 35 | W16: 35
B17: ABX464 Revenue | N17: =+N16*N14 -> 0 | O17: =+O16*(O14+O15) -> 94433.367 | P17: =+P16*(P14+P15) -> 357088.01 | Q17: =+Q16*(Q14+Q15) -> 693530.56 | R17: =+R16*(R14+R15) -> 1029973.1 | S17: =+S16*(S14+S15) -> 1319199 | T17: =+T16*(T14+T15) -> 1571530.9 | U17: =+U16*(U14+U15) -> 1714476.9 | V17: =+V16*(V14+V15) -> 1767191.9 | W17: =+W16*(W14+W15) -> 1819510 | X17: =+W17*0.8 -> 1455608 | Y17: =+X17*0.8 -> 1164486.4 | Z17: =+Y17*0.8 -> 931589.1 | AA17: =+Z17*0.8 -> 745271.28 | AB17: =+AA17*0.8 -> 596217.02
B18: Other Income | L18: =6815*2 -> 13630 | M18: =+L18*1.02 -> 13902.6 | N18: =+M18*1.02 -> 14180.652 | O18: =+N18*1.02 -> 14464.265 | P18: =+O18*1.02 -> 14753.55 | Q18: =+P18*1.02 -> 15048.621 | R18: =+Q18*1.02 -> 15349.594 | S18: =+R18*1.02 -> 15656.586 | T18: =+S18*1.02 -> 15969.717 | ... AB18: =+AA18*1.02 -> 18711.069
B19: COGS | L19: =+L17*0.2 -> 0 | M19: =+M17*0.2 -> 0 | N19: =+N17*0.2 -> 0 | O19: =+O17*0.2 -> 18886.673 | P19: =+P17*0.2 -> 71417.602 | Q19: =+Q17*0.2 -> 138706.11 | R19: =+R17*0.2 -> 205994.62 | S19: =+S17*0.2 -> 263839.8 | ... AB19: =+AB17*0.2 -> 119243.4
B20: Gross Margin | L20: =+L17-L19+L18 -> 13630 | M20: =+M17-M19+M18 -> 13902.6 | N20: =+N17-N19+N18 -> 14180.652 | O20: =+O17-O19+O18 -> 90010.959 | P20: =+P17-P19+P18 -> 300423.96 | Q20: =+Q17-Q19+Q18 -> 569873.07 | R20: =+R17-R19+R18 -> 839328.08 | S20: =+S17-S19+S18 -> 1071015.8 | ... AB20: =+AB17-AB19+AB18 -> 495684.69
B21: R&D | L21: =64650*2.5 -> 161625 | M21: 150000 | N21: 150000 | O21: 150000 | P21: =+O21*0.98 -> 147000 | Q21: =+P21*0.98 -> 144060 | R21: =+Q21*0.98 -> 141178.8 | S21: =+R21*0.98 -> 138355.22 | T21: =+S21*0.98 -> 135588.12 | U21: =+T21*0.98 -> 132876.36 | V21: =+U21*0.98 -> 130218.83 | W21: =+V21*0.98 -> 127614.45 | ... AB21: =+AA21*0.98 -> 115353.36
B22: SG&A | L22: =(4229+17932)*2.5 -> 55402.5 | M22: 50000 | N22: 50000 | O22: 50000 | P22: =+P17*0.3 -> 107126.4 | Q22: =+Q17*0.3 -> 208059.17 | R22: =+R17*0.3 -> 308991.93 | S22: =+S17*0.3 -> 395759.69 | T22: =+T17*0.3 -> 471459.27 | U22: =+U17*0.3 -> 514343.08 | V22: =+V17*0.3 -> 530157.57 | W22: =+W17*0.3 -> 545852.99 | ... AB22: =+AB17*0.3 -> 178865.11
B23: Operating Income | L23: =+L20-L21-L22 -> -203397.5 | M23: =+M20-M21-M22 -> -186097.4 | N23: =+N20-N21-N22 -> -185819.35 | O23: =+O20-O21-O22 -> -109989.04 | P23: =+P20-P21-P22 -> 46297.555 | Q23: =+Q20-Q21-Q22 -> 217753.9 | R23: =+R20-R21-R22 -> 389157.35 | S23: =+S20-S21-S22 -> 536900.85 | ... AB23: =+AB20-AB21-AB22 -> 201466.22
B24: Interest Expense | L24: =9514*2 -> 19028 | M24: =+L24*0.9 -> 17125.2 | N24: =+M24*0.9 -> 15412.68 | O24: =+N24*0.9 -> 13871.412 | P24: =+O24*0.9 -> 12484.271 | Q24: =+P24*0.9 -> 11235.844 | R24: =+Q24*0.9 -> 10112.259 | S24: =+R24*0.9 -> 9101.0334 | T24: =+S24*0.9 -> 8190.9301 | ... AB24: =+AA24*0.9 -> 3525.9268
B25: Interest Income | L25: =7873*2 -> 15746 | M25: =+L25*0.9 -> 14171.4 | N25: =+M25*0.9 -> 12754.26 | O25: =+N25*0.9 -> 11478.834 | P25: =+O25*0.9 -> 10330.951 | Q25: =+P25*0.9 -> 9297.8555 | R25: =+Q25*0.9 -> 8368.07 | S25: =+R25*0.9 -> 7531.263 | T25: =+S25*0.9 -> 6778.1367 | ... AB25: =+AA25*0.9 -> 2917.7656
B26: Pretax | L26: =+L23-L24+L25 -> -206679.5 | M26: =+M23-M24+M25 -> -189051.2 | N26: =+N23-N24+N25 -> -188477.77 | O26: =+O23-O24+O25 -> -112381.62 | P26: =+P23-P24+P25 -> 44144.235 | Q26: =+Q23-Q24+Q25 -> 215815.91 | R26: =+R23-R24+R25 -> 387413.16 | S26: =+S23-S24+S25 -> 535331.08 | ... AB26: =+AB23-AB24+AB25 -> 200858.06
B27: Taxes | L27: 0 | O27: =+O26*0.25 -> -28095.405 | P27: =+P26*0.25 -> 11036.059 | Q27: =+Q26*0.25 -> 53953.978 | R27: =+R26*0.25 -> 96853.29 | S27: =+S26*0.25 -> 133832.77 | T27: =+T26*0.25 -> 166183.56 | U27: =+U26*0.25 -> 184844.93 | V27: =+V26*0.25 -> 192211.91 | ... AB27: =+AB26*0.25 -> 50214.515
B28: Net Income | L28: =+L26-L27 -> -206679.5 | M28: =+M26-M27 -> -189051.2 | N28: =+N26-N27 -> -188477.77 | O28: =+O26-O27 -> -84286.215 | P28: =+P26-P27 -> 33108.176 | Q28: =+Q26-Q27 -> 161861.93 | R28: =+R26-R27 -> 290559.87 | S28: =+S26-S27 -> 401498.31 | ... AB28: =+AB26-AB27 -> 150643.55 | AC28: =+AB28*(1+TR) -> 143111.37 | AD28: =+AC28*(1+TR) -> 135955.8 | AE28: =+AD28*(1+TR) -> 129158.01 | AF28: =+AE28*(1+TR) -> 122700.11 | AG28: =+AF28*(1+TR) -> 116565.1 | AH28: =+AG28*(1+TR) -> 110736.85 | AI28: =+AH28*(1+TR) -> 105200.01 | AJ28: =+AI28*(1+TR) -> 99940.006 | ... BF28: =+BE28*(1+TR) -> 32333.944
B30: Gross Margin | N30: =+N20/(N17+N18) -> 1 | O30: =+O20/(O17+O18) -> 0.82656488 | P30: =+P20/(P17+P18) -> 0.8079354 | Q30: =+Q20/(Q17+Q18) -> 0.80424755 | R30: =+R20/(R17+R18) -> 0.80293681 | S30: =+S20/(S17+S18) -> 0.80234581 | T30: =+T20/(T17+T18) -> 0.80201193 | U30: =+U20/(U17+U18) -> 0.8018823 | ... AB30: =+AB20/(AB17+AB18) -> 0.80608561 | AD30: Discount | AE30: 0.1
B31: Net Margin | N31: =+N28/(N17+N18) -> -13.291192 | O31: =+O28/(O17+O18) -> -0.77399493 | P31: =+P28/(P17+P18) -> 0.089038396 | Q31: =+Q28/(Q17+Q18) -> 0.22843168 | R31: =+R28/(R17+R18) -> 0.27796189 | S31: =+S28/(S17+S18) -> 0.30078034 | T31: =+T28/(T17+T18) -> 0.31404756 | U31: =+U28/(U17+U18) -> 0.32039846 | ... AB31: =+AB28/(AB17+AB18) -> 0.2449775 | AD31: Terminal | AE31: -0.05
AD32: NPV | AE32: =NPV(AE30,L28:BF28) -> 1277573.8
M33: =+M28+N28+O28+P28-100000 -> -528707.01 | AD33: Net Cash | AE33: =+Main!K12-Main!K13 -> 102700
AD34: Value | AE34: =+AE32+AE33 -> 1380273.8
AD35: Price | AE35: =+AE34/Main!K16 -> 32.440722
