Workbook

Sheet Main
B2: Price | C2: 392.5
B3: Shares | C3: 338000
B4: MC | C4: =+C2*C3 -> 132665000
B5: Net Cash | C5: =2487096-3512987 -> -1025891
B6: EV | C6: =+C4-C5 -> 133690891
B8: EV/FCF | C8: =+C6/Base!G29 -> 35.819447
B9: FCF Yield | C9: =1/C8 -> 0.027917796
B11: Case | C11: Weight | D11: EV
B12: Bear | C12: 0.3 | D12: =+C12*Bear!T24 -> 59.971813
B13: Base | C13: 0.5 | D13: =+C13*Base!T24 -> 221.11025
B14: Bull | C14: 0.2 | D14: =+C14*Bull!T24 -> 142.84286
B16: Prob. EV | C16: =+SUM(D12:D14) -> 423.92492

Sheet Base
D2: 2022 | E2: =+D2+1 -> 2023 | F2: =+E2+1 -> 2024 | G2: =+F2+1 -> 2025 | H2: =+G2+1 -> 2026 | I2: =+H2+1 -> 2027 | J2: =+I2+1 -> 2028 | K2: =+J2+1 -> 2029 | L2: =+K2+1 -> 2030 | ... Q2: =+P2+1 -> 2035
B5: Revenue | F5: 3224058 | G5: 5480717 | H5: =+G5*1.3 -> 7124932.1 | I5: =+H5*1.27 -> 9048663.8 | J5: =+I5*1.24 -> 11220343 | K5: =+J5*1.2 -> 13464412 | L5: =+K5*1.17 -> 15753362 | M5: =+L5*1.15 -> 18116366 | N5: =+M5*1.13 -> 20471493 | O5: =+N5*1.11 -> 22723358 | P5: =+O5*1.1 -> 24995694 | Q5: =+P5*1.09 -> 27245306
B6: COGS | F6: 520613 | G6: 665140 | H6: =+H5*0.12 -> 854991.85 | I6: =+I5*0.12 -> 1085839.7 | J6: =+J5*0.12 -> 1346441.2 | K6: =+K5*0.12 -> 1615729.4 | L6: =+L5*0.12 -> 1890403.4 | M6: =+M5*0.12 -> 2173963.9 | N6: =+N5*0.12 -> 2456579.2 | O6: =+O5*0.12 -> 2726802.9 | ... Q6: =+Q5*0.12 -> 3269436.7
B7: Gross profit | D7: =+D5-D6 -> 0 | E7: =+E5-E6 -> 0 | F7: =+F5-F6 -> 2703445 | G7: =+G5-G6 -> 4815577 | H7: =+H5-H6 -> 6269940.2 | I7: =+I5-I6 -> 7962824.1 | J7: =+J5-J6 -> 9873901.9 | K7: =+K5-K6 -> 11848682 | ... Q7: =+Q5-Q6 -> 23975869
B8: S&M | F8: 252863 | G8: 203651 | H8: =+G8*(1+H22*0.666666666666667) -> 244381.2 | I8: =+H8*(1+I22*0.666666666666667) -> 288369.82 | J8: =+I8*(1+J22*0.666666666666667) -> 334508.99 | K8: =+J8*(1+K22*0.666666666666667) -> 379110.18 | L8: =+K8*(1+L22*0.666666666666667) -> 422076.01 | M8: =+L8*(1+M22*0.666666666666667) -> 464283.61 | N8: =+M8*(1+N22*0.666666666666667) -> 504521.52 | O8: =+N8*(1+O22*0.666666666666667) -> 541519.76 | ... Q8: =+P8*(1+Q22*0.666666666666667) -> 612278.35
B9: R&D | F9: 374710 | G9: 226510 | H9: =+G9*(1+H22*0.666666666666667) -> 271812 | I9: =+H9*(1+I22*0.666666666666667) -> 320738.16 | J9: =+I9*(1+J22*0.666666666666667) -> 372056.27 | K9: =+J9*(1+K22*0.666666666666667) -> 421663.77 | L9: =+K9*(1+L22*0.666666666666667) -> 469452.33 | M9: =+L9*(1+M22*0.666666666666667) -> 516397.56 | N9: =+M9*(1+N22*0.666666666666667) -> 561152.02 | O9: =+N9*(1+O22*0.666666666666667) -> 602303.16 | ... Q9: =+P9*(1+Q22*0.666666666666667) -> 681004.11
B10: G&A | F10: 164916 | G10: 233502 | H10: =+H5*0.045 -> 320621.94 | I10: =+I5*0.045 -> 407189.87 | J10: =+J5*0.045 -> 504915.44 | K10: =+K5*0.045 -> 605898.53 | L10: =+L5*0.045 -> 708901.28 | M10: =+M5*0.045 -> 815236.47 | N10: =+N5*0.045 -> 921217.21 | O10: =+O5*0.045 -> 1022551.1 | ... Q10: =+Q5*0.045 -> 1226038.8
B11: Operating Income | D11: =+D7-SUM(D8:D10) -> 0 | E11: =+E7-SUM(E8:E10) -> 0 | F11: =+F7-SUM(F8:F10) -> 1910956 | G11: =+G7-SUM(G8:G10) -> 4151914 | H11: =+H7-SUM(H8:H10) -> 5433125.1 | I11: =+I7-SUM(I8:I10) -> 6946526.3 | J11: =+J7-SUM(J8:J10) -> 8662421.2 | K11: =+K7-SUM(K8:K10) -> 10442010 | ... Q11: =+Q7-SUM(Q8:Q10) -> 21456548
B12: Interest Expense | F12: 317209 | G12: 207016 | H12: =+G12*0.98 -> 202875.68 | I12: =+H12*0.98 -> 198818.17 | J12: =+I12*0.98 -> 194841.8 | K12: =+J12*0.98 -> 190944.97 | L12: =+K12*0.98 -> 187126.07 | M12: =+L12*0.98 -> 183383.55 | N12: =+M12*0.98 -> 179715.88 | O12: =+N12*0.98 -> 176121.56 | ... Q12: =+P12*0.98 -> 169147.14
B13: Other income, net | F13: 18196 | G13: 8012 | H13: 5000 | I13: 5000 | J13: 5000 | K13: 5000 | L13: 5000 | M13: 5000 | N13: 5000 | O13: 5000 | P13: 5000 | Q13: 5000
B14: Pretax | D14: =+D11-D12+D13 -> 0 | E14: =+E11-E12+E13 -> 0 | F14: =+F11-F12+F13 -> 1611943 | G14: =+G11-G12+G13 -> 3952910 | H14: =+H11-H12+H13 -> 5235249.4 | I14: =+I11-I12+I13 -> 6752708.1 | J14: =+J11-J12+J13 -> 8472579.4 | K14: =+K11-K12+K13 -> 10256065 | ... Q14: =+Q11-Q12+Q13 -> 21292401
B15: Taxes | F15: 22419 | G15: 519715 | H15: =+H14*0.21 -> 1099402.4 | I15: =+I14*0.21 -> 1418068.7 | J15: =+J14*0.21 -> 1779241.7 | K15: =+K14*0.21 -> 2153773.6 | L15: =+L14*0.21 -> 2536884.5 | M15: =+M14*0.21 -> 2933301.2 | N15: =+N14*0.21 -> 3329194.6 | O15: =+O14*0.21 -> 3708402.4 | ... Q15: =+Q14*0.21 -> 4471404.2
B16: Net Income | D16: =+D14-D15 -> 0 | E16: =+E14-E15 -> 0 | F16: =+F14-F15 -> 1589524 | G16: =+G14-G15 -> 3433195 | H16: =+H14-H15 -> 4135847 | I16: =+I14-I15 -> 5334639.4 | J16: =+J14-J15 -> 6693337.7 | K16: =+K14-K15 -> 8102291.2 | ... Q16: =+Q14-Q15 -> 16820997 | R16: =+Q16*(1+$T21) -> 17325627 | S16: =+R16*(1+$T21) -> 17845395 | T16: =+S16*(1+$T21) -> 18380757 | U16: =+T16*(1+$T21) -> 18932180 | V16: =+U16*(1+$T21) -> 19500145 | W16: =+V16*(1+$T21) -> 20085150 | X16: =+W16*(1+$T21) -> 20687704 | Y16: =+X16*(1+$T21) -> 21308335 | ... FE16: =+FD16*(1+$T21) -> 1.1868944e+09
B17: EPS | F17: =+F16/F18 -> 4.5701191 | G17: =+G16/G18 -> 10.039463 | H17: =+H16/H18 -> 12.094181 | I17: =+I16/I18 -> 15.599729 | J17: =+J16/J18 -> 19.57288 | K17: =+K16/K18 -> 23.692988 | L17: =+L16/L18 -> 27.907472 | M17: =+M16/M18 -> 32.268327 | ... Q17: =+Q16/Q18 -> 49.188516
B18: Shares | F18: 347808 | G18: 341970 | H18: 341970 | I18: 341970 | J18: 341970 | K18: 341970 | L18: 341970 | M18: 341970 | N18: 341970 | O18: 341970 | P18: 341970 | Q18: 341970
B20: Gross margin | F20: =+F7/F5 -> 0.83852245 | G20: =+G7/G5 -> 0.87863997 | H20: =+H7/H5 -> 0.88 | I20: =+I7/I5 -> 0.88 | J20: =+J7/J5 -> 0.88 | K20: =+K7/K5 -> 0.88 | L20: =+L7/L5 -> 0.88 | M20: =+M7/M5 -> 0.88 | ... Q20: =+Q7/Q5 -> 0.88 | S20: Discount | T20: 0.1
B21: Operating Margin | F21: =+F11/F5 -> 0.59271762 | G21: =+G11/G5 -> 0.75754942 | H21: =+H11/H5 -> 0.76255114 | I21: =+I11/I5 -> 0.76768531 | J21: =+J11/J5 -> 0.7720282 | K21: =+K11/K5 -> 0.77552663 | L21: =+L11/L5 -> 0.77840711 | M21: =+M11/M5 -> 0.78086767 | ... Q21: =+Q11/Q5 -> 0.78753192 | S21: Terminal | T21: 0.03
B22: Revenue Y/Y | G22: =+G5/F5 -1 -> 0.69994367 | H22: =+H5/G5 -1 -> 0.3 | I22: =+I5/H5 -1 -> 0.27 | J22: =+J5/I5 -1 -> 0.24 | K22: =+K5/J5 -1 -> 0.2 | L22: =+L5/K5 -1 -> 0.17 | M22: =+M5/L5 -1 -> 0.15 | N22: =+N5/M5 -1 -> 0.13 | ... Q22: =+Q5/P5 -1 -> 0.09 | S22: NPV | T22: =NPV(T20,H16:FE16) -> 1.5225203e+08
S23: Value | T23: =+T22+Main!C5 -> 1.5122614e+08
B24: D&A | F24: 448680 | G24: 194778 | S24: Price | T24: =+T23/Q18 -> 442.22049
B25: SBC | F25: 369367 | G25: 210421
B26: CFFO | F26: 2099011 | G26: 3971094
B27: CapEx | F27: 25553 | G27: 28318
B28: FCF | F28: =+F26-F27 -> 2073458 | G28: =+G26-G27 -> 3942776
B29: Adj. FCF | F29: =+F28-F25 -> 1704091 | G29: =+G28-G25 -> 3732355
B31: S&M | F31: =+F8/F$5 -> 0.078430041 | G31: =+G8/G$5 -> 0.03715773
B32: R&D | F32: =+F9/F$5 -> 0.1162231 | G32: =+G9/G$5 -> 0.041328534
B33: G&A | F33: =+F10/F$5 -> 0.051151685 | G33: =+G10/G$5 -> 0.04260428
B35: Cash | F35: 697030 | G35: 2487096
B36: Debt | F36: 3508983 | G36: 3512987
B37: Net Debt | F37: =+F36-F35 -> 2811953 | G37: =+G36-G35 -> 1025891
B38: Cost of Debt | F38: =+F12/F36 -> 0.090399127 | G38: =+G12/G36 -> 0.058928769

Sheet Bull
D2: 2022 | E2: =+D2+1 -> 2023 | F2: =+E2+1 -> 2024 | G2: =+F2+1 -> 2025 | H2: =+G2+1 -> 2026 | I2: =+H2+1 -> 2027 | J2: =+I2+1 -> 2028 | K2: =+J2+1 -> 2029 | L2: =+K2+1 -> 2030 | ... Q2: =+P2+1 -> 2035
B5: Revenue | F5: 3224058 | G5: 5480717 | H5: =+G5*(1+H22) -> 7398968 | I5: =+H5*(1+I22) -> 9840627.4 | J5: =+I5*(1+J22) -> 12792816 | K5: =+J5*(1+K22) -> 16246876 | L5: =+K5*(1+L22) -> 20308595 | M5: =+L5*(1+M22) -> 24979572 | N5: =+M5*(1+N22) -> 29975486 | O5: =+N5*(1+O22) -> 35371073 | ... Q5: =+P5*(1+Q22) -> 46774707
B6: COGS | F6: 520613 | G6: 665140 | H6: =+H5*0.12 -> 887876.15 | I6: =+I5*0.12 -> 1180875.3 | J6: =+J5*0.12 -> 1535137.9 | K6: =+K5*0.12 -> 1949625.1 | L6: =+L5*0.12 -> 2437031.4 | M6: =+M5*0.12 -> 2997548.6 | N6: =+N5*0.12 -> 3597058.3 | O6: =+O5*0.12 -> 4244528.8 | ... Q6: =+Q5*0.12 -> 5612964.9
B7: Gross profit | D7: =+D5-D6 -> 0 | E7: =+E5-E6 -> 0 | F7: =+F5-F6 -> 2703445 | G7: =+G5-G6 -> 4815577 | H7: =+H5-H6 -> 6511091.8 | I7: =+I5-I6 -> 8659752.1 | J7: =+J5-J6 -> 11257678 | K7: =+K5-K6 -> 14297251 | ... Q7: =+Q5-Q6 -> 41161742
B8: S&M | F8: 252863 | G8: 203651 | H8: =+G8*(1+H22*0.666666666666667) -> 251169.57 | I8: =+H8*(1+I22*0.666666666666667) -> 306426.87 | J8: =+I8*(1+J22*0.666666666666667) -> 367712.25 | K8: =+J8*(1+K22*0.666666666666667) -> 433900.45 | L8: =+K8*(1+L22*0.666666666666667) -> 506217.19 | M8: =+L8*(1+M22*0.666666666666667) -> 583837.16 | N8: =+M8*(1+N22*0.666666666666667) -> 661682.12 | O8: =+N8*(1+O22*0.666666666666667) -> 741083.97 | ... Q8: =+P8*(1+Q22*0.666666666666667) -> 896678.67
B9: R&D | F9: 374710 | G9: 226510 | H9: =+G9*(1+H22*0.666666666666667) -> 279362.33 | I9: =+H9*(1+I22*0.666666666666667) -> 340822.05 | J9: =+I9*(1+J22*0.666666666666667) -> 408986.46 | K9: =+J9*(1+K22*0.666666666666667) -> 482604.02 | L9: =+K9*(1+L22*0.666666666666667) -> 563038.02 | M9: =+L9*(1+M22*0.666666666666667) -> 649370.52 | N9: =+M9*(1+N22*0.666666666666667) -> 735953.25 | O9: =+N9*(1+O22*0.666666666666667) -> 824267.64 | ... Q9: =+P9*(1+Q22*0.666666666666667) -> 997327.21
B10: G&A | F10: 164916 | G10: 233502 | H10: =+H5*0.045 -> 332953.56 | I10: =+I5*0.045 -> 442828.23 | J10: =+J5*0.045 -> 575676.7 | K10: =+K5*0.045 -> 731109.41 | L10: =+L5*0.045 -> 913886.76 | M10: =+M5*0.045 -> 1124080.7 | N10: =+N5*0.045 -> 1348896.9 | O10: =+O5*0.045 -> 1591698.3 | ... Q10: =+Q5*0.045 -> 2104861.8
B11: Operating Income | D11: =+D7-SUM(D8:D10) -> 0 | E11: =+E7-SUM(E8:E10) -> 0 | F11: =+F7-SUM(F8:F10) -> 1910956 | G11: =+G7-SUM(G8:G10) -> 4151914 | H11: =+H7-SUM(H8:H10) -> 5647606.3 | I11: =+I7-SUM(I8:I10) -> 7569674.9 | J11: =+J7-SUM(J8:J10) -> 9905302.3 | K11: =+K7-SUM(K8:K10) -> 12649637 | ... Q11: =+Q7-SUM(Q8:Q10) -> 37162875
B12: Interest Expense | F12: 317209 | G12: 207016 | H12: =+G12*0.98 -> 202875.68 | I12: =+H12*0.98 -> 198818.17 | J12: =+I12*0.98 -> 194841.8 | K12: =+J12*0.98 -> 190944.97 | L12: =+K12*0.98 -> 187126.07 | M12: =+L12*0.98 -> 183383.55 | N12: =+M12*0.98 -> 179715.88 | O12: =+N12*0.98 -> 176121.56 | ... Q12: =+P12*0.98 -> 169147.14
B13: Other income, net | F13: 18196 | G13: 8012 | H13: 5000 | I13: 5000 | J13: 5000 | K13: 5000 | L13: 5000 | M13: 5000 | N13: 5000 | O13: 5000 | P13: 5000 | Q13: 5000
B14: Pretax | D14: =+D11-D12+D13 -> 0 | E14: =+E11-E12+E13 -> 0 | F14: =+F11-F12+F13 -> 1611943 | G14: =+G11-G12+G13 -> 3952910 | H14: =+H11-H12+H13 -> 5449730.7 | I14: =+I11-I12+I13 -> 7375856.8 | J14: =+J11-J12+J13 -> 9715460.5 | K14: =+K11-K12+K13 -> 12463692 | ... Q14: =+Q11-Q12+Q13 -> 36998728
B15: Taxes | F15: 22419 | G15: 519715 | H15: =+H14*0.21 -> 1144443.4 | I15: =+I14*0.21 -> 1548929.9 | J15: =+J14*0.21 -> 2040246.7 | K15: =+K14*0.21 -> 2617375.3 | L15: =+L14*0.21 -> 3298322 | M15: =+M14*0.21 -> 4083733.7 | N15: =+N14*0.21 -> 4926007.7 | O15: =+O14*0.21 -> 5837658.3 | ... Q15: =+Q14*0.21 -> 7769732.8
B16: Net Income | D16: =+D14-D15 -> 0 | E16: =+E14-E15 -> 0 | F16: =+F14-F15 -> 1589524 | G16: =+G14-G15 -> 3433195 | H16: =+H14-H15 -> 4305287.2 | I16: =+I14-I15 -> 5826926.9 | J16: =+J14-J15 -> 7675213.8 | K16: =+K14-K15 -> 9846316.6 | ... Q16: =+Q14-Q15 -> 29228995 | R16: =+Q16*(1+$T21) -> 30105865 | S16: =+R16*(1+$T21) -> 31009041 | T16: =+S16*(1+$T21) -> 31939312 | U16: =+T16*(1+$T21) -> 32897491 | V16: =+U16*(1+$T21) -> 33884416 | W16: =+V16*(1+$T21) -> 34900948 | X16: =+W16*(1+$T21) -> 35947977 | Y16: =+X16*(1+$T21) -> 37026416 | ... FE16: =+FD16*(1+$T21) -> 2.0624064e+09
B17: EPS | F17: =+F16/F18 -> 4.5701191 | G17: =+G16/G18 -> 10.039463 | H17: =+H16/H18 -> 12.589663 | I17: =+I16/I18 -> 17.039292 | J17: =+J16/J18 -> 22.444114 | K17: =+K16/K18 -> 28.792925 | L17: =+L16/L18 -> 36.283807 | M17: =+M16/M18 -> 44.923874 | ... Q17: =+Q16/Q18 -> 85.472395
B18: Shares | F18: 347808 | G18: 341970 | H18: 341970 | I18: 341970 | J18: 341970 | K18: 341970 | L18: 341970 | M18: 341970 | N18: 341970 | O18: 341970 | P18: 341970 | Q18: 341970
B20: Gross margin | F20: =+F7/F5 -> 0.83852245 | G20: =+G7/G5 -> 0.87863997 | H20: =+H7/H5 -> 0.88 | I20: =+I7/I5 -> 0.88 | J20: =+J7/J5 -> 0.88 | K20: =+K7/K5 -> 0.88 | L20: =+L7/L5 -> 0.88 | M20: =+M7/M5 -> 0.88 | ... Q20: =+Q7/Q5 -> 0.88 | S20: Discount | T20: 0.1
B21: Operating Margin | F21: =+F11/F5 -> 0.59271762 | G21: =+G11/G5 -> 0.75754942 | H21: =+H11/H5 -> 0.7632965 | I21: =+I11/I5 -> 0.76922686 | J21: =+J11/J5 -> 0.77428634 | K21: =+K11/K5 -> 0.77858888 | L21: =+L11/L5 -> 0.78234962 | M21: =+M11/M5 -> 0.78563135 | ... Q21: =+Q11/Q5 -> 0.79450791 | S21: Terminal | T21: 0.03
B22: Revenue Y/Y | G22: =+G5/F5 -1 -> 0.69994367 | H22: 0.35 | I22: 0.33 | J22: 0.3 | K22: 0.27 | L22: 0.25 | M22: 0.23 | N22: 0.2 | O22: 0.18 | P22: 0.16 | Q22: 0.14 | S22: NPV | T22: =NPV(T20,H16:FE16) -> 2.4526575e+08
S23: Value | T23: =+T22+Main!C5 -> 2.4423986e+08
B24: D&A | F24: 448680 | G24: 194778 | S24: Price | T24: =+T23/Q18 -> 714.21429
B25: SBC | F25: 369367 | G25: 210421
B26: CFFO | F26: 2099011 | G26: 3971094
B27: CapEx | F27: 25553 | G27: 28318
B28: FCF | F28: =+F26-F27 -> 2073458 | G28: =+G26-G27 -> 3942776
B29: Adj. FCF | F29: =+F28-F25 -> 1704091 | G29: =+G28-G25 -> 3732355
B31: S&M | F31: =+F8/F$5 -> 0.078430041 | G31: =+G8/G$5 -> 0.03715773
B32: R&D | F32: =+F9/F$5 -> 0.1162231 | G32: =+G9/G$5 -> 0.041328534
B33: G&A | F33: =+F10/F$5 -> 0.051151685 | G33: =+G10/G$5 -> 0.04260428
B35: Cash | F35: 697030 | G35: 2487096
B36: Debt | F36: 3508983 | G36: 3512987
B37: Net Debt | F37: =+F36-F35 -> 2811953 | G37: =+G36-G35 -> 1025891
B38: Cost of Debt | F38: =+F12/F36 -> 0.090399127 | G38: =+G12/G36 -> 0.058928769

Sheet Bear
D2: 2022 | E2: =+D2+1 -> 2023 | F2: =+E2+1 -> 2024 | G2: =+F2+1 -> 2025 | H2: =+G2+1 -> 2026 | I2: =+H2+1 -> 2027 | J2: =+I2+1 -> 2028 | K2: =+J2+1 -> 2029 | L2: =+K2+1 -> 2030 | ... Q2: =+P2+1 -> 2035
B5: Revenue | F5: 3224058 | G5: 5480717 | H5: =+G5*(1+H22) -> 6686474.7 | I5: =+H5*(1+I22) -> 7689446 | J5: =+I5*(1+J22) -> 8304601.6 | K5: =+J5*(1+K22) -> 8719831.7 | L5: =+K5*(1+L22) -> 9068625 | M5: =+L5*(1+M22) -> 9431370 | N5: =+M5*(1+N22) -> 9808624.8 | O5: =+N5*(1+O22) -> 10200970 | ... Q5: =+P5*(1+Q22) -> 11033369
B6: COGS | F6: 520613 | G6: 665140 | H6: =+H5*0.12 -> 802376.97 | I6: =+I5*0.12 -> 922733.51 | J6: =+J5*0.12 -> 996552.2 | K6: =+K5*0.12 -> 1046379.8 | L6: =+L5*0.12 -> 1088235 | M6: =+M5*0.12 -> 1131764.4 | N6: =+N5*0.12 -> 1177035 | O6: =+O5*0.12 -> 1224116.4 | ... Q6: =+Q5*0.12 -> 1324004.3
B7: Gross profit | D7: =+D5-D6 -> 0 | E7: =+E5-E6 -> 0 | F7: =+F5-F6 -> 2703445 | G7: =+G5-G6 -> 4815577 | H7: =+H5-H6 -> 5884097.8 | I7: =+I5-I6 -> 6766712.4 | J7: =+J5-J6 -> 7308049.4 | K7: =+K5-K6 -> 7673451.9 | ... Q7: =+Q5-Q6 -> 9709364.6
B8: S&M | F8: 252863 | G8: 203651 | H8: =+G8*(1+H22*0.666666666666667) -> 233519.81 | I8: =+H8*(1+I22*0.666666666666667) -> 256871.79 | J8: =+I8*(1+J22*0.666666666666667) -> 270571.62 | K8: =+J8*(1+K22*0.666666666666667) -> 279590.68 | L8: =+K8*(1+L22*0.666666666666667) -> 287046.43 | M8: =+L8*(1+M22*0.666666666666667) -> 294701 | N8: =+M8*(1+N22*0.666666666666667) -> 302559.69 | O8: =+N8*(1+O22*0.666666666666667) -> 310627.95 | ... Q8: =+P8*(1+Q22*0.666666666666667) -> 327415.67
B9: R&D | F9: 374710 | G9: 226510 | H9: =+G9*(1+H22*0.666666666666667) -> 259731.47 | I9: =+H9*(1+I22*0.666666666666667) -> 285704.61 | J9: =+I9*(1+J22*0.666666666666667) -> 300942.19 | K9: =+J9*(1+K22*0.666666666666667) -> 310973.6 | L9: =+K9*(1+L22*0.666666666666667) -> 319266.23 | M9: =+L9*(1+M22*0.666666666666667) -> 327779.99 | N9: =+M9*(1+N22*0.666666666666667) -> 336520.79 | O9: =+N9*(1+O22*0.666666666666667) -> 345494.68 | ... Q9: =+P9*(1+Q22*0.666666666666667) -> 364166.75
B10: G&A | F10: 164916 | G10: 233502 | H10: =+H5*0.045 -> 300891.36 | I10: =+I5*0.045 -> 346025.07 | J10: =+J5*0.045 -> 373707.07 | K10: =+K5*0.045 -> 392392.43 | L10: =+L5*0.045 -> 408088.12 | M10: =+M5*0.045 -> 424411.65 | N10: =+N5*0.045 -> 441388.11 | O10: =+O5*0.045 -> 459043.64 | ... Q10: =+Q5*0.045 -> 496501.6
B11: Operating Income | D11: =+D7-SUM(D8:D10) -> 0 | E11: =+E7-SUM(E8:E10) -> 0 | F11: =+F7-SUM(F8:F10) -> 1910956 | G11: =+G7-SUM(G8:G10) -> 4151914 | H11: =+H7-SUM(H8:H10) -> 5089955.1 | I11: =+I7-SUM(I8:I10) -> 5878111 | J11: =+J7-SUM(J8:J10) -> 6362828.5 | K11: =+K7-SUM(K8:K10) -> 6690495.2 | ... Q11: =+Q7-SUM(Q8:Q10) -> 8521280.6
B12: Interest Expense | F12: 317209 | G12: 207016 | H12: =+G12*0.98 -> 202875.68 | I12: =+H12*0.98 -> 198818.17 | J12: =+I12*0.98 -> 194841.8 | K12: =+J12*0.98 -> 190944.97 | L12: =+K12*0.98 -> 187126.07 | M12: =+L12*0.98 -> 183383.55 | N12: =+M12*0.98 -> 179715.88 | O12: =+N12*0.98 -> 176121.56 | ... Q12: =+P12*0.98 -> 169147.14
B13: Other income, net | F13: 18196 | G13: 8012 | H13: 5000 | I13: 5000 | J13: 5000 | K13: 5000 | L13: 5000 | M13: 5000 | N13: 5000 | O13: 5000 | P13: 5000 | Q13: 5000
B14: Pretax | D14: =+D11-D12+D13 -> 0 | E14: =+E11-E12+E13 -> 0 | F14: =+F11-F12+F13 -> 1611943 | G14: =+G11-G12+G13 -> 3952910 | H14: =+H11-H12+H13 -> 4892079.4 | I14: =+I11-I12+I13 -> 5684292.8 | J14: =+J11-J12+J13 -> 6172986.7 | K14: =+K11-K12+K13 -> 6504550.2 | ... Q14: =+Q11-Q12+Q13 -> 8357133.5
B15: Taxes | F15: 22419 | G15: 519715 | H15: =+H14*0.21 -> 1027336.7 | I15: =+I14*0.21 -> 1193701.5 | J15: =+J14*0.21 -> 1296327.2 | K15: =+K14*0.21 -> 1365955.5 | L15: =+L14*0.21 -> 1424611.3 | M15: =+M14*0.21 -> 1485609.2 | N15: =+N14*0.21 -> 1549045.1 | O15: =+O14*0.21 -> 1615018.8 | ... Q15: =+Q14*0.21 -> 1754998
B16: Net Income | D16: =+D14-D15 -> 0 | E16: =+E14-E15 -> 0 | F16: =+F14-F15 -> 1589524 | G16: =+G14-G15 -> 3433195 | H16: =+H14-H15 -> 3864742.8 | I16: =+I14-I15 -> 4490591.3 | J16: =+J14-J15 -> 4876659.5 | K16: =+K14-K15 -> 5138594.7 | ... Q16: =+Q14-Q15 -> 6602135.4 | R16: =+Q16*(1+$T21) -> 6800199.5 | S16: =+R16*(1+$T21) -> 7004205.5 | T16: =+S16*(1+$T21) -> 7214331.7 | U16: =+T16*(1+$T21) -> 7430761.6 | V16: =+U16*(1+$T21) -> 7653684.5 | W16: =+V16*(1+$T21) -> 7883295 | X16: =+W16*(1+$T21) -> 8119793.8 | Y16: =+X16*(1+$T21) -> 8363387.6 | ... FE16: =+FD16*(1+$T21) -> 4.6584859e+08
B17: EPS | F17: =+F16/F18 -> 4.5701191 | G17: =+G16/G18 -> 10.039463 | H17: =+H16/H18 -> 11.301409 | I17: =+I16/I18 -> 13.131536 | J17: =+J16/J18 -> 14.260489 | K17: =+K16/K18 -> 15.026449 | L17: =+L16/L18 -> 15.671702 | M17: =+M16/M18 -> 16.342721 | ... Q17: =+Q16/Q18 -> 19.306183
B18: Shares | F18: 347808 | G18: 341970 | H18: 341970 | I18: 341970 | J18: 341970 | K18: 341970 | L18: 341970 | M18: 341970 | N18: 341970 | O18: 341970 | P18: 341970 | Q18: 341970
B20: Gross margin | F20: =+F7/F5 -> 0.83852245 | G20: =+G7/G5 -> 0.87863997 | H20: =+H7/H5 -> 0.88 | I20: =+I7/I5 -> 0.88 | J20: =+J7/J5 -> 0.88 | K20: =+K7/K5 -> 0.88 | L20: =+L7/L5 -> 0.88 | M20: =+M7/M5 -> 0.88 | ... Q20: =+Q7/Q5 -> 0.88 | S20: Discount | T20: 0.1
B21: Operating Margin | F21: =+F11/F5 -> 0.59271762 | G21: =+G11/G5 -> 0.75754942 | H21: =+H11/H5 -> 0.76123149 | I21: =+I11/I5 -> 0.76443882 | J21: =+J11/J5 -> 0.76618107 | K21: =+K11/K5 -> 0.76727343 | L21: =+L11/L5 -> 0.76814172 | M21: =+M11/M5 -> 0.76899888 | ... Q21: =+Q11/Q5 -> 0.77231902 | S21: Terminal | T21: 0.03
B22: Revenue Y/Y | G22: =+G5/F5 -1 -> 0.69994367 | H22: 0.22 | I22: 0.15 | J22: 0.08 | K22: 0.05 | L22: 0.04 | M22: 0.04 | N22: 0.04 | O22: 0.04 | P22: 0.04 | Q22: 0.04 | S22: NPV | T22: =NPV(T20,H16:FE16) -> 69387761
S23: Value | T23: =+T22+Main!C5 -> 68361870
B24: D&A | F24: 448680 | G24: 194778 | S24: Price | T24: =+T23/Q18 -> 199.90604
B25: SBC | F25: 369367 | G25: 210421
B26: CFFO | F26: 2099011 | G26: 3971094
B27: CapEx | F27: 25553 | G27: 28318
B28: FCF | F28: =+F26-F27 -> 2073458 | G28: =+G26-G27 -> 3942776
B29: Adj. FCF | F29: =+F28-F25 -> 1704091 | G29: =+G28-G25 -> 3732355
B31: S&M | F31: =+F8/F$5 -> 0.078430041 | G31: =+G8/G$5 -> 0.03715773
B32: R&D | F32: =+F9/F$5 -> 0.1162231 | G32: =+G9/G$5 -> 0.041328534
B33: G&A | F33: =+F10/F$5 -> 0.051151685 | G33: =+G10/G$5 -> 0.04260428
B35: Cash | F35: 697030 | G35: 2487096
B36: Debt | F36: 3508983 | G36: 3512987
B37: Net Debt | F37: =+F36-F35 -> 2811953 | G37: =+G36-G35 -> 1025891
B38: Cost of Debt | F38: =+F12/F36 -> 0.090399127 | G38: =+G12/G36 -> 0.058928769
