Workbook
Name TR: Model!$AF$88

Sheet Main
B3: 2023 | C3: Trucks NA | D3: Mercedes | E3: Trucks Asia | F3: Daimler Buses | G3: Financials | H3: Total | I3: Recon
B4: Europe | C4: 180 | D4: 14397 | E4: 480 | F4: 3039 | G4: 104 | H4: =+SUM(C4:G4) -> 18200 | I4: 1046 | J4: =+H4-I4 -> 17154
B5: NA | C5: 22964 | D5: 1197 | E5: 108 | F5: 440 | G5: 37 | H5: =+SUM(C5:G5) -> 24746 | I5: 1288 | J5: =+H5-I5 -> 23458
B6: Asia | C6: 6 | D6: 1953 | E6: 5721 | F6: 94 | G6: 15 | H6: =+SUM(C6:G6) -> 7789 | I6: 716 | J6: =+H6-I6 -> 7073
B7: Latin America | C7: 122 | D7: 2281 | E7: 171 | F7: 700 | G7: 21 | H7: =+SUM(C7:G7) -> 3295 | I7: 249 | J7: =+H7-I7 -> 3046
B8: Other Markets | C8: 190 | D8: 1157 | E8: 533 | F8: 102 | G8: 39 | H8: =+SUM(C8:G8) -> 2021 | I8: 42 | J8: =+H8-I8 -> 1979
B9: Other Revenue | C9: 29 | D9: 652 | E9: 47 | F9: 192 | G9: 2458 | H9: =+SUM(C9:G9) -> 3378 | I9: 199 | J9: =+H9-I9 -> 3179
B10: Total | C10: =+SUM(C4:C9) -> 23491 | D10: =+SUM(D4:D9) -> 21637 | E10: =+SUM(E4:E9) -> 7060 | F10: =+SUM(F4:F9) -> 4567 | G10: =+SUM(G4:G9) -> 2674 | H10: =+SUM(H4:H9) -> 59429 | I10: =+SUM(I4:I9) -> 3540 | J10: =+SUM(J4:J9) -> 55889
B13: 2022 | C13: Trucks NA | D13: Mercedes | E13: Trucks Asia | F13: Daimler Buses | G13: Financials | H13: Total | I13: Recon
B14: Europe | C14: 207 | D14: 12213 | E14: 381 | F14: 2456 | G14: 42 | H14: =+SUM(C14:G14) -> 15299 | I14: 864 | J14: =+H14-I14 -> 14435
B15: NA | C15: 21408 | D15: 1182 | E15: 130 | F15: 256 | G15: 46 | H15: =+SUM(C15:G15) -> 23022 | I15: 1285 | J15: =+H15-I15 -> 21737
B16: Asia | C16: 8 | D16: 1905 | E16: 5166 | F16: 62 | G16: 17 | H16: =+SUM(C16:G16) -> 7158 | I16: 689 | J16: =+H16-I16 -> 6469
B17: Latin America | C17: 175 | D17: 3442 | E17: 222 | F17: 643 | G17: 22 | H17: =+SUM(C17:G17) -> 4504 | I17: 253 | J17: =+H17-I17 -> 4251
B18: Other Markets | C18: 187 | D18: 908 | E18: 567 | F18: 77 | G18: 49 | H18: =+SUM(C18:G18) -> 1788 | I18: 48 | J18: =+H18-I18 -> 1740
B19: Other Revenue | C19: 54 | D19: 563 | E19: 33 | F19: 195 | G19: 1583 | H19: =+SUM(C19:G19) -> 2428 | I19: 115 | J19: =+H19-I19 -> 2313
B20: Total | C20: =+SUM(C14:C19) -> 22039 | D20: =+SUM(D14:D19) -> 20213 | E20: =+SUM(E14:E19) -> 6499 | F20: =+SUM(F14:F19) -> 3689 | G20: =+SUM(G14:G19) -> 1759 | H20: =+SUM(H14:H19) -> 54199 | I20: =+SUM(I14:I19) -> 3254 | J20: =+SUM(J14:J19) -> 50945

Sheet Model
C2: H1 23 | D2: H2 23 | E2: H1 24 | F2: H2 24 | O2: 2022 | P2: =+O2+1 -> 2023 | Q2: =+P2+1 -> 2024 | R2: =+Q2+1 -> 2025 | S2: =+R2+1 -> 2026 | T2: =+S2+1 -> 2027 | U2: =+T2+1 -> 2028 | V2: =+U2+1 -> 2029 | W2: =+V2+1 -> 2030 | ... AB2: =+AA2+1 -> 2035
B4: Units | O4: =+SUM(O5:O8) -> 533156 | P4: =+SUM(P5:P8) -> 540864 | Q4: =+SUM(Q5:Q8) -> 468785 | R4: =+SUM(R5:R8) -> 424698.8 | S4: =+SUM(S5:S8) -> 453496.57 | T4: =+SUM(T5:T8) -> 561567.27 | U4: =+SUM(U5:U8) -> 584304.93 | V4: =+SUM(V5:V8) -> 588948.82 | ... AB4: =+SUM(AB5:AB8) -> 687309.21
B5: Trucks NA | C5: 99509 | D5: =+P5-C5 -> 95505 | E5: 94450 | F5: 93000 | O5: 186779 | P5: 195014 | Q5: 190428 | R5: =+Q5*0.75 -> 142821 | S5: =+R5*1.125 -> 160673.62 | T5: =+S5*1.6 -> 257077.8 | U5: =+T5*1.04 -> 267360.91 | V5: =+U5*0.97 -> 259340.08 | W5: =+V5*1.02 -> 264526.89 | X5: =+W5*1.015 -> 268494.79 | Y5: =+X5*1.015 -> 272522.21 | Z5: =+Y5*1.015 -> 276610.04 | AA5: =+Z5*1.015 -> 280759.2 | AB5: =+AA5*1.015 -> 284970.58
B6: Mercedes Trucks | C6: 73728 | D6: =+P6-C6 -> 84783 | E6: 62489 | F6: 60000 | O6: 166369 | P6: 158511 | Q6: 126477 | R6: =+Q6*0.96 -> 121417.92 | S6: =+R6*1.035 -> 125667.55 | T6: =+S6*1.035 -> 130065.91 | U6: =+T6*1.035 -> 134618.22 | V6: =+U6*1.035 -> 139329.86 | W6: =+V6*1.035 -> 144206.4 | X6: =+W6*1.035 -> 149253.62 | Y6: =+X6*1.035 -> 154477.5 | Z6: =+Y6*1.035 -> 159884.21 | ... AB6: =+AA6*1.035 -> 171271.97
B7: Trucks Asia | C7: 80307 | D7: =+P7-C7 -> 80864 | E7: 65799 | F7: 60000 | O7: 155967 | P7: 161171 | Q7: 125234 | R7: =+Q7*1.06 -> 132748.04 | S7: =+R7*1.04 -> 138057.96 | T7: =+S7*1.04 -> 143580.28 | U7: =+T7*1.04 -> 149323.49 | V7: =+U7*1.04 -> 155296.43 | W7: =+V7*1.04 -> 161508.29 | X7: =+W7*1.03 -> 166353.54 | Y7: =+X7*1.03 -> 171344.14 | Z7: =+Y7*1.03 -> 176484.47 | AA7: =+Z7*1.03 -> 181779 | AB7: =+AA7*1.03 -> 187232.37
B8: Daimler Buses | C8: 11751 | D8: =+P8-C8 -> 14417 | E8: 12252 | F8: 15000 | O8: 24041 | P8: 26168 | Q8: 26646 | R8: =+Q8*1.04 -> 27711.84 | S8: =+R8*1.05 -> 29097.432 | T8: =+S8*1.06 -> 30843.278 | U8: =+T8*1.07 -> 33002.307 | V8: =+U8*1.06 -> 34982.446 | W8: =+V8*1.05 -> 36731.568 | X8: =+W8*1.04 -> 38200.831 | Y8: =+X8*1.04 -> 39728.864 | Z8: =+Y8*1.04 -> 41318.019 | AA8: =+Z8*1.03 -> 42557.559 | AB8: =+AA8*1.03 -> 43834.286
B10: Revenue/Unit | O10: =+O82/O4 *1000000 -> 95553.647 | P10: =+P82/P4 *1000000 -> 103334.66 | Q10: =+Q82/Q4 *1000000 -> 115355.65 | R10: =+R82/R4 *1000000 -> 111520.76 | S10: =+S82/S4 *1000000 -> 113864.16 | T10: =+T82/T4 *1000000 -> 119569.58 | U10: =+U82/U4 *1000000 -> 123437.84 | V10: =+V82/V4 *1000000 -> 127035.91 | ... AB10: =+AB82/AB4 *1000000 -> 152894.51
B11: Trucks NA | C11: =+C30/C5 *1000000 -> 118361.15 | D11: =+D30/D5 *1000000 -> 122642.79 | E11: =+E30/E5 *1000000 -> 125177.34 | F11: 125000 | O11: =+O30/O5 *1000000 -> 117995.06 | P11: =+P30/P5 *1000000 -> 120458.02 | Q11: =+Q30/Q5 *1000000 -> 124881.85 | R11: 135000 | S11: 135000 | T11: =+S11*1.03 -> 139050 | U11: =+T11*1.03 -> 143221.5 | V11: =+U11*1.03 -> 147518.14 | W11: =+V11*1.03 -> 151943.69 | X11: =+W11*1.03 -> 156502 | Y11: =+X11*1.03 -> 161197.06 | Z11: =+Y11*1.03 -> 166032.97 | AA11: =+Z11*1.03 -> 171013.96 | AB11: =+AA11*1.03 -> 176144.38
B12: Mercedes | C12: =+C31/C6 *1000000 -> 142998.59 | D12: =+D31/D6 *1000000 -> 130851.7 | E12: =+E31/E6 *1000000 -> 150554.5 | F12: 150000 | O12: =+O31/O6 *1000000 -> 121494.99 | P12: =+P31/P6 *1000000 -> 136501.57 | Q12: =+Q31/Q6 *1000000 -> 150976.07 | R12: 130000 | S12: 135000 | T12: =+S12*1.03 -> 139050 | U12: =+T12*1.03 -> 143221.5 | V12: =+U12*1.03 -> 147518.14 | W12: =+V12*1.03 -> 151943.69 | X12: =+W12*1.03 -> 156502 | Y12: =+X12*1.03 -> 161197.06 | Z12: =+Y12*1.03 -> 166032.97 | AA12: =+Z12*1.03 -> 171013.96 | AB12: =+AA12*1.03 -> 176144.38
B13: Trucks Asia | C13: =+C32/C7 *1000000 -> 42922.784 | D13: =+D32/D7 *1000000 -> 44679.956 | E13: =+E32/E7 *1000000 -> 44286.387 | F13: 44000 | O13: =+O32/O7 *1000000 -> 41669.071 | P13: =+P32/P7 *1000000 -> 43804.406 | Q13: =+Q32/Q7 *1000000 -> 48796.653 | R13: 46000 | S13: 45000 | T13: =+S13*1.03 -> 46350 | U13: =+T13*1.03 -> 47740.5 | V13: =+U13*1.03 -> 49172.715 | W13: =+V13*1.03 -> 50647.896 | X13: =+W13*1.03 -> 52167.333 | Y13: =+X13*1.03 -> 53732.353 | Z13: =+Y13*1.03 -> 55344.324 | AA13: =+Z13*1.03 -> 57004.654 | AB13: =+AA13*1.03 -> 58714.793
B14: Daimler Buses | C14: =+C33/C8 *1000000 -> 164071.14 | D14: =+D33/D8 *1000000 -> 183047.79 | E14: =+E33/E8 *1000000 -> 199314.4 | F14: 200000 | O14: =+O33/O8 *1000000 -> 153446.2 | P14: =+P33/P8 *1000000 -> 174526.14 | Q14: =+Q33/Q8 *1000000 -> 196915.11 | R14: 213000 | S14: =+R14*1.06 -> 225780 | T14: =+S14*1.05 -> 237069 | U14: =+T14*1.05 -> 248922.45 | V14: =+U14*1.05 -> 261368.57 | W14: =+V14*1.05 -> 274437 | X14: =+W14*1.05 -> 288158.85 | Y14: =+X14*1.05 -> 302566.79 | Z14: =+Y14*1.05 -> 317695.13 | AA14: =+Z14*1.05 -> 333579.89 | AB14: =+AA14*1.05 -> 350258.88
B16: EBIT/Unit
B17: Trucks NA | C17: =+C74/C5 *1000000 -> 14651.941 | D17: =+D74/D5 *1000000 -> 14962.567 | E17: =+E74/E5 *1000000 -> 16919.005 | F17: =+F74/F5 *1000000 -> 16875 | O17: =+O74/O5 *1000000 -> 12720.916 | P17: =+P74/P5 *1000000 -> 14804.065 | Q17: =+Q74/Q5 *1000000 -> 15795.996 | R17: =+R74/R5 *1000000 -> 16875 | S17: =+S74/S5 *1000000 -> 16875 | T17: =+T74/T5 *1000000 -> 17381.25 | U17: =+U74/U5 *1000000 -> 17902.688 | V17: =+V74/V5 *1000000 -> 18439.768 | ... Y17: =+Y74/Y5 *1000000 -> 20149.633
B18: Mercedes | C18: =+C75/C6 *1000000 -> 12858.073 | D18: =+D75/D6 *1000000 -> 12856.351 | E18: =+E75/E6 *1000000 -> 10033.766 | F18: =+F75/F6 *1000000 -> 10500 | O18: =+O75/O6 *1000000 -> 7140.7534 | P18: =+P75/P6 *1000000 -> 12857.152 | Q18: =+Q75/Q6 *1000000 -> 8554.9151 | R18: =+R75/R6 *1000000 -> 7800 | S18: =+S75/S6 *1000000 -> 8100 | T18: =+T75/T6 *1000000 -> 8343 | U18: =+U75/U6 *1000000 -> 8593.29 | V18: =+V75/V6 *1000000 -> 8851.0887 | ... Y18: =+Y75/Y6 *1000000 -> 9671.8236
B19: Trucks Asia | C19: =+C76/C7 *1000000 -> 2129.3287 | D19: =+D76/D7 *1000000 -> 1966.2643 | E19: =+E76/E7 *1000000 -> -501.52738 | F19: =+F76/F7 *1000000 -> -440 | O19: =+O76/O7 *1000000 -> 1032.2696 | P19: =+P76/P7 *1000000 -> 2047.5148 | Q19: =+Q76/Q7 *1000000 -> 503.05827 | R19: =+R76/R7 *1000000 -> 920 | S19: =+S76/S7 *1000000 -> 900 | T19: =+T76/T7 *1000000 -> 1158.75 | U19: =+U76/U7 *1000000 -> 1432.215 | V19: =+V76/V7 *1000000 -> 1475.1815 | ... Y19: =+Y76/Y7 *1000000 -> 1611.9706
B20: Daimler Buses | C20: =+C77/C8 *1000000 -> 3574.1639 | D20: =+D77/D8 *1000000 -> 11930.36 | E20: =+E77/E8 *1000000 -> 14201.763 | F20: =+F77/F8 *1000000 -> 15000 | O20: =+O77/O8 *1000000 -> -2162.9716 | P20: =+P77/P8 *1000000 -> 8177.9272 | Q20: =+Q77/Q8 *1000000 -> 16024.919 | R20: =+R77/R8 *1000000 -> 17040 | S20: =+S77/S8 *1000000 -> 18513.96 | T20: =+T77/T8 *1000000 -> 19913.796 | U20: =+U77/U8 *1000000 -> 21407.331 | V20: =+V77/V8 *1000000 -> 23000.434 | ... Y20: =+Y77/Y8 *1000000 -> 28441.279
B22: EBIT Margin
B23: Trucks NA | C23: =+C74/C30 -> 0.12379012 | D23: =+D74/D30 -> 0.1220012 | E23: =+E74/E30 -> 0.13516028 | F23: 0.135 | O23: =+O74/O30 -> 0.10780888 | P23: =+P74/P30 -> 0.12289813 | Q23: =+Q74/Q30 -> 0.12648753 | R23: 0.125 | S23: 0.125 | T23: 0.125 | U23: 0.125 | V23: 0.125 | W23: 0.125 | X23: 0.125 | Y23: 0.125 | Z23: 0.125 | AA23: 0.125 | AB23: 0.125
B24: Mercedes | C24: =+C75/C31 -> 0.089917481 | D24: =+D75/D31 -> 0.098251307 | E24: =+E75/E31 -> 0.066645408 | F24: 0.07 | O24: =+O75/O31 -> 0.058774056 | P24: =+P75/P31 -> 0.094190507 | Q24: =+Q75/Q31 -> 0.056664048 | R24: 0.06 | S24: 0.06 | T24: 0.06 | U24: 0.06 | V24: 0.06 | W24: 0.06 | X24: 0.06 | Y24: 0.06 | Z24: 0.06 | AA24: 0.06 | AB24: 0.06
B25: Trucks Asia | C25: =+C76/C32 -> 0.049608355 | D25: =+D76/D32 -> 0.04400775 | E25: =+E76/E32 -> -0.01132464 | F25: -0.01 | O25: =+O76/O32 -> 0.024773042 | P25: =+P76/P32 -> 0.04674221 | Q25: =+Q76/Q32 -> 0.010309278 | R25: 0.02 | S25: 0.02 | T25: 0.025 | U25: 0.03 | V25: 0.03 | W25: 0.03 | X25: 0.03 | Y25: 0.03 | Z25: 0.03 | AA25: 0.03 | AB25: 0.03
B26: Daimler Buses | C26: =+C77/C33 -> 0.021784232 | D26: =+D77/D33 -> 0.065176203 | E26: =+E77/E33 -> 0.071253071 | F26: 0.075 | O26: =+O77/O33 -> -0.014095961 | P26: =+P77/P33 -> 0.046857894 | Q26: =+Q77/Q33 -> 0.081379836 | R26: 0.08 | S26: =+R26+0.002 -> 0.082 | T26: =+S26+0.002 -> 0.084 | U26: =+T26+0.002 -> 0.086 | V26: =+U26+0.002 -> 0.088 | W26: =+V26+0.002 -> 0.09 | X26: =+W26+0.002 -> 0.092 | Y26: =+X26+0.002 -> 0.094 | Z26: =+Y26+0.002 -> 0.096 | ... AB26: =+AA26+0.002 -> 0.1
B27: Financial Service | C27: =+C78/C34 -> 0.079581994 | D27: =+D78/D34 -> 0.060839161 | E27: =+E78/E34 -> 0.037888199 | F27: 0.035 | O27: =+O78/O34 -> 0.1762365 | P27: =+P78/P34 -> 0.069558714 | Q27: =+Q78/Q34 -> 0.031793641 | R27: 0.035 | S27: 0.035 | T27: 0.035 | U27: 0.035 | V27: 0.035 | W27: 0.035 | X27: 0.035 | Y27: 0.035 | Z27: 0.035 | AA27: 0.035 | AB27: 0.035
B29: Revenue
B30: Trucks NA | C30: 11778 | D30: =+P30-C30 -> 11713 | E30: 11823 | F30: =+F11*F5/1000000 -> 11625 | O30: =+Main!C20 -> 22039 | P30: =+Main!C10 -> 23491 | Q30: 23781 | R30: =+R5*R11/1000000 -> 19280.835 | S30: =+S5*S11/1000000 -> 21690.939 | T30: =+T5*T11/1000000 -> 35746.668 | U30: =+U5*U11/1000000 -> 38291.831 | V30: =+V5*V11/1000000 -> 38257.368 | W30: =+W5*W11/1000000 -> 40193.191 | X30: =+X5*X11/1000000 -> 42019.972 | Y30: =+Y5*Y11/1000000 -> 43929.779 | ... AB30: =+AB5*AB11/1000000 -> 50195.967
B31: Mercedes | C31: 10543 | D31: =+P31-C31 -> 11094 | E31: 9408 | F31: =+F12*F6/1000000 -> 9000 | O31: =+Main!D20 -> 20213 | P31: =+Main!D10 -> 21637 | Q31: 19095 | R31: =+R6*R12/1000000 -> 15784.33 | S31: =+S6*S12/1000000 -> 16965.119 | T31: =+T6*T12/1000000 -> 18085.665 | U31: =+U6*U12/1000000 -> 19280.223 | V31: =+V6*V12/1000000 -> 20553.682 | W31: =+W6*W12/1000000 -> 21911.253 | X31: =+X6*X12/1000000 -> 23358.491 | Y31: =+Y6*Y12/1000000 -> 24901.319 | ... AB31: =+AB6*AB12/1000000 -> 30168.594
B32: Trucks Asia | C32: 3447 | D32: =+P32-C32 -> 3613 | E32: 2914 | F32: =+F13*F7/1000000 -> 2640 | O32: =+Main!E20 -> 6499 | P32: =+Main!E10 -> 7060 | Q32: 6111 | R32: =+R7*R13/1000000 -> 6106.4098 | S32: =+S7*S13/1000000 -> 6212.6083 | T32: =+T7*T13/1000000 -> 6654.946 | U32: =+U7*U13/1000000 -> 7128.7781 | V32: =+V7*V13/1000000 -> 7636.3471 | W32: =+W7*W13/1000000 -> 8180.0551 | X32: =+X7*X13/1000000 -> 8678.2204 | Y32: =+Y7*Y13/1000000 -> 9206.724 | ... AB32: =+AB7*AB13/1000000 -> 10993.31
B33: Daimler Buses | C33: 1928 | D33: =+P33-C33 -> 2639 | E33: 2442 | F33: =+F14*F8/1000000 -> 3000 | O33: =+Main!F20 -> 3689 | P33: =+Main!F10 -> 4567 | Q33: 5247 | R33: =+R8*R14/1000000 -> 5902.6219 | S33: =+S8*S14/1000000 -> 6569.6182 | T33: =+T8*T14/1000000 -> 7311.9851 | U33: =+U8*U14/1000000 -> 8215.0152 | V33: =+V8*V14/1000000 -> 9143.3119 | W33: =+W8*W14/1000000 -> 10080.501 | X33: =+X8*X14/1000000 -> 11007.908 | Y33: =+Y8*Y14/1000000 -> 12020.635 | ... AB33: =+AB8*AB14/1000000 -> 15353.348
B34: Financial Service | C34: 1244 | D34: =+P34-C34 -> 1430 | E34: 1610 | F34: 1700 | O34: =+Main!G20 -> 1759 | P34: =+Main!G10 -> 2674 | Q34: 3334 | R34: 3500 | S34: =+R34+200 -> 3700 | T34: =+S34+200 -> 3900 | U34: =+T34+200 -> 4100 | V34: =+U34+200 -> 4300 | W34: =+V34+200 -> 4500 | X34: =+W34+200 -> 4700 | Y34: =+X34+200 -> 4900 | Z34: =+Y34+200 -> 5100 | ... AB34: =+AA34+200 -> 5500
B35: Reconsiliation | O35: =-Main!I20 -> -3254 | P35: =-Main!I10 -> -3540 | Q35: =-0.0635*SUM(Q30:Q34) -> -3655.568 | R35: =-0.0635*SUM(R30:R34) -> -3211.4615 | S35: =-0.0635*SUM(S30:S34) -> -3501.2811 | T35: =-0.0635*SUM(T30:T34) -> -4552.9033 | U35: =-0.0635*SUM(U30:U34) -> -4890.5063 | V35: =-0.0635*SUM(V30:V34) -> -5073.06 | W35: =-0.0635*SUM(W30:W34) -> -5388.9275 | X35: =-0.0635*SUM(X30:X34) -> -5700.0515 | ... AB35: =-0.0635*SUM(AB30:AB34) -> -7125.4124
B37: COGS
B38: Trucks NA | O38: 18178 | P38: 18922
B39: Mercedes | O39: 16533 | P39: 16750
B40: Trucks Asia | O40: 5353 | P40: 5732
B41: Daimler Buses | O41: 3261 | P41: 3846
B43: Gross Profit
B44: Trucks NA | O44: =+O30-O38 -> 3861 | P44: =+P30-P38 -> 4569
B45: Mercedes | O45: =+O31-O39 -> 3680 | P45: =+P31-P39 -> 4887
B46: Trucks Asia | O46: =+O32-O40 -> 1146 | P46: =+P32-P40 -> 1328
B47: Daimler Buses | O47: =+O33-O41 -> 428 | P47: =+P33-P41 -> 721
B49: Selling
B50: Trucks NA | O50: 432 | P50: 420
B51: Mercedes | O51: 1586 | P51: 1590
B52: Trucks Asia | O52: 658 | P52: 615
B53: Daimler Buses | O53: 247 | P53: 263
B55: G&A
B56: Trucks NA | O56: 609 | P56: 750
B57: Mercedes | O57: 724 | P57: 1045
B58: Trucks Asia | O58: 243 | P58: 292
B59: Daimler Buses | O59: 221 | P59: 198
B61: R&D
B62: Trucks NA | O62: 599 | P62: 663 | Q62: 721
B63: Mercedes | O63: 616 | P63: 801 | Q63: 784
B64: Trucks Asia | O64: 161 | P64: 179 | Q64: 157
B65: Daimler Buses | O65: 134 | P65: 172 | Q65: 193
B67: Other Income
B68: Trucks NA | O68: 155 | P68: 126
B69: Mercedes | O69: 433 | P69: 482
B70: Trucks Asia | O70: 77 | P70: 69
B71: Daimler Buses | O71: 123 | P71: 120
B73: EBIT
B74: Trucks NA | C74: 1458 | D74: =+P74-C74 -> 1429 | E74: 1598 | F74: =+F30*F23 -> 1569.375 | O74: 2376 | P74: 2887 | Q74: 3008 | R74: =+R30*R23 -> 2410.1044 | S74: =+S30*S23 -> 2711.3674 | T74: =+T30*T23 -> 4468.3335 | U74: =+U30*U23 -> 4786.4789 | V74: =+V30*V23 -> 4782.171 | W74: =+W30*W23 -> 5024.1489 | X74: =+X30*X23 -> 5252.4964 | Y74: =+Y30*Y23 -> 5491.2224 | ... AB74: =+AB30*AB23 -> 6274.4958
B75: Mercedes | C75: 948 | D75: =+P75-C75 -> 1090 | E75: 627 | F75: =+F31*F24 -> 630 | O75: 1188 | P75: 2038 | Q75: 1082 | R75: =+R31*R24 -> 947.05978 | S75: =+S31*S24 -> 1017.9071 | T75: =+T31*T24 -> 1085.1399 | U75: =+U31*U24 -> 1156.8134 | V75: =+V31*V24 -> 1233.2209 | W75: =+W31*W24 -> 1314.6752 | X75: =+X31*X24 -> 1401.5094 | Y75: =+Y31*Y24 -> 1494.0791 | ... AB75: =+AB31*AB24 -> 1810.1157
B76: Trucks Asia | C76: 171 | D76: =+P76-C76 -> 159 | E76: -33 | F76: =+F32*F25 -> -26.4 | O76: 161 | P76: 330 | Q76: 63 | R76: =+R32*R25 -> 122.1282 | S76: =+S32*S25 -> 124.25217 | T76: =+T32*T25 -> 166.37365 | U76: =+U32*U25 -> 213.86334 | V76: =+V32*V25 -> 229.09041 | W76: =+W32*W25 -> 245.40165 | X76: =+X32*X25 -> 260.34661 | Y76: =+Y32*Y25 -> 276.20172 | ... AB76: =+AB32*AB25 -> 329.7993
B77: Daimler Buses | C77: 42 | D77: =+P77-C77 -> 172 | E77: 174 | F77: =+F33*F26 -> 225 | O77: -52 | P77: 214 | Q77: 427 | R77: =+R33*R26 -> 472.20975 | S77: =+S33*S26 -> 538.70869 | T77: =+T33*T26 -> 614.20674 | U77: =+U33*U26 -> 706.49131 | V77: =+V33*V26 -> 804.61145 | W77: =+W33*W26 -> 907.24513 | X77: =+X33*X26 -> 1012.7275 | Y77: =+Y33*Y26 -> 1129.9397 | ... AB77: =+AB33*AB26 -> 1535.3348
B78: Financial Service | C78: 99 | D78: =+P78-C78 -> 87 | E78: 61 | F78: =+F34*F27 -> 59.5 | O78: 310 | P78: 186 | Q78: 106 | R78: =+R34*R27 -> 122.5 | S78: =+S34*S27 -> 129.5 | T78: =+T34*T27 -> 136.5 | U78: =+U34*U27 -> 143.5 | V78: =+V34*V27 -> 150.5 | W78: =+W34*W27 -> 157.5 | X78: =+X34*X27 -> 164.5 | Y78: =+Y34*Y27 -> 171.5 | ... AB78: =+AB34*AB27 -> 192.5
B79: Reconsiliation | O79: =+O92-SUM(O74:O78) -> -487 | P79: -471 | Q79: =+Q35*0.15 -> -548.3352 | R79: =+R35*0.15 -> -481.71922 | S79: =+S35*0.15 -> -525.19216 | T79: =+T35*0.15 -> -682.93549 | U79: =+U35*0.15 -> -733.57595 | V79: =+V35*0.15 -> -760.959 | W79: =+W35*0.15 -> -808.33913 | X79: =+X35*0.15 -> -855.00772 | ... AB79: =+AB35*0.15 -> -1068.8119
B82: Revenue | O82: 50945 | P82: 55890 | Q82: 54077 | R82: =+SUM(R30:R35) -> 47362.735 | S82: =+SUM(S30:S35) -> 51637.004 | T82: =+SUM(T30:T35) -> 67146.361 | U82: =+SUM(U30:U35) -> 72125.341 | V82: =+SUM(V30:V35) -> 74817.649 | W82: =+SUM(W30:W35) -> 79476.073 | X82: =+SUM(X30:X35) -> 84064.539 | Y82: =+SUM(Y30:Y35) -> 88928.595 | ... AB82: =+SUM(AB30:AB35) -> 105085.81
B83: COGS | O83: 41513 | P83: 43968 | Q83: 42879 | R83: =+R82*0.78 -> 36942.933
B84: Profit | O84: =+O82-O83 -> 9432 | P84: =+P82-P83 -> 11922 | Q84: =+Q82-Q83 -> 11198 | R84: =+R82-R83 -> 10419.802
B85: Selling | O85: 2928 | P85: 2890 | Q85: 3009 | R85: =+Q85*0.995 -> 2993.955
B86: G&A | O86: 1957 | P86: 2413 | Q86: 2582 | R86: =+Q86*1.04 -> 2685.28
B87: R&D | O87: 1618 | P87: 1757 | Q87: 1671 | R87: =+Q87*1.04 -> 1737.84
B88: Other Income | O88: 880 | P88: 664 | Q88: 696 | R88: 500 | AE88: Terminal | AF88: 0.01
B89: Other Expense | O89: 177 | P89: 101 | Q89: 417 | R89: 150 | AE89: Discount | AF89: 0.1
B90: Equity, net | O90: -226 | P90: -109 | Q90: -603 | R90: -50 | AE90: NPV | AF90: =NPV(AF89,R108:DO108) -> 47920.738
B91: Finance, net | O91: 90 | P91: -132 | Q91: -19 | R91: 50 | AE91: Shares | AF91: 804.09361
B92: EBIT | O92: =+O84-O85-O86-O87+O88-O89+O90+O91 -> 3496 | P92: =+P84-P85-P86-P87+P88-P89+P90+P91 -> 5184 | Q92: =+Q84-Q85-Q86-Q87+Q88-Q89+Q90+Q91 -> 3593 | R92: =+SUM(R74:R79) -> 3592.2829 | S92: =+SUM(S74:S79) -> 3996.5432 | T92: =+SUM(T74:T79) -> 5787.6183 | U92: =+SUM(U74:U79) -> 6273.571 | V92: =+SUM(V74:V79) -> 6438.6348 | W92: =+SUM(W74:W79) -> 6840.6317 | X92: =+SUM(X74:X79) -> 7236.5723 | Y92: =+SUM(Y74:Y79) -> 7658.4637 | ... AB92: =+SUM(AB74:AB79) -> 9073.4337 | AE92: Price | AF92: =+AF90/AF91 -> 59.595969
B93: Interest Income | O93: 198 | P93: 384 | Q93: 430 | R93: =+Q93*0.98 -> 421.4 | S93: =+R93*0.98 -> 412.972 | T93: =+S93*0.98 -> 404.71256 | U93: =+T93*0.98 -> 396.61831 | V93: =+U93*0.98 -> 388.68594 | W93: =+V93*0.98 -> 380.91222 | X93: =+W93*0.98 -> 373.29398 | Y93: =+X93*0.98 -> 365.8281 | ... AB93: =+AA93*0.98 -> 344.31448
B94: Interest Expense | O94: 245 | P94: 241 | Q94: 220 | R94: =+Q94*1.02 -> 224.4 | S94: =+R94*1.02 -> 228.888 | T94: =+S94*1.02 -> 233.46576 | U94: =+T94*1.02 -> 238.13508 | V94: =+U94*1.02 -> 242.89778 | W94: =+V94*1.02 -> 247.75573 | X94: =+W94*1.02 -> 252.71085 | Y94: =+X94*1.02 -> 257.76506 | ... AB94: =+AA94*1.02 -> 273.54235
B95: Pretax | O95: =+O92-O94+O93 -> 3449 | P95: =+P92-P94+P93 -> 5327 | Q95: =+Q92-Q94+Q93 -> 3803 | R95: =+R92-R94+R93 -> 3789.2829 | S95: =+S92-S94+S93 -> 4180.6272 | T95: =+T92-T94+T93 -> 5958.8651 | U95: =+U92-U94+U93 -> 6432.0542 | V95: =+V92-V94+V93 -> 6584.423 | ... AB95: =+AB92-AB94+AB93 -> 9144.2059
B96: Taxes | O96: 686 | P96: 1355 | Q96: 736 | R96: =+R95*0.25 -> 947.32072 | S96: =+S95*0.25 -> 1045.1568 | T96: =+T95*0.25 -> 1489.7163 | U96: =+U95*0.25 -> 1608.0135 | V96: =+V95*0.25 -> 1646.1057 | W96: =+W95*0.25 -> 1743.447 | X96: =+X95*0.25 -> 1839.2889 | Y96: =+Y95*0.25 -> 1941.6317 | ... AB96: =+AB95*0.25 -> 2286.0515
B97: Net Income | O97: =+O95-O96 -> 2763 | P97: =+P95-P96 -> 3972 | Q97: =+Q95-Q96 -> 3067 | R97: =+R95-R96 -> 2841.9622 | S97: =+S95-S96 -> 3135.4704 | T97: =+T95-T96 -> 4469.1488 | U97: =+U95-U96 -> 4824.0406 | V97: =+V95-V96 -> 4938.3172 | ... AB97: =+AB95-AB96 -> 6858.1544
B98: Minority | O98: 98 | P98: 196 | Q98: 166 | R98: 180 | S98: 180 | T98: 180 | U98: 180 | V98: 180 | W98: 180 | X98: 180 | Y98: 180 | Z98: 180 | AA98: 180 | AB98: 180
B99: Company Income | O99: =+O97-O98 -> 2665 | P99: =+P97-P98 -> 3776 | Q99: =+Q97-Q98 -> 2901 | R99: =+R97-R98 -> 2661.9622 | S99: =+S97-S98 -> 2955.4704 | T99: =+T97-T98 -> 4289.1488 | U99: =+U97-U98 -> 4644.0406 | V99: =+V97-V98 -> 4758.3172 | ... AB99: =+AB97-AB98 -> 6678.1544
B101: Gross Margin | O101: =+O84/O82 -> 0.18514084 | P101: =+P84/P82 -> 0.21331186
B102: EBIT Margin | O102: =+O92/O82 -> 0.068623025 | P102: =+P92/P82 -> 0.092753623 | Q102: =+Q92/Q82 -> 0.066442295 | R102: =+R92/R82 -> 0.075846188 | S102: =+S92/S82 -> 0.077396885 | T102: =+T92/T82 -> 0.086194073 | U102: =+U92/U82 -> 0.086981508 | V102: =+V92/V82 -> 0.0860577 | ... AB102: =+AB92/AB82 -> 0.086343095
B103: Net Margin | O103: =+O97/O82 -> 0.054234959 | P103: =+P97/P82 -> 0.07106817 | Q103: =+Q97/Q82 -> 0.056715424 | R103: =+R97/R82 -> 0.060004182 | S103: =+S97/S82 -> 0.060721386 | T103: =+T97/T82 -> 0.066558318 | U103: =+U97/U82 -> 0.066884129 | V103: =+V97/V82 -> 0.06600471 | ... AB103: =+AB97/AB82 -> 0.065262423
B105: D&A | P105: 1133 | Q105: 1153 | R105: =+Q105+20 -> 1173 | S105: =+R105+20 -> 1193 | T105: =+S105+20 -> 1213 | U105: =+T105+20 -> 1233 | V105: =+U105+20 -> 1253 | W105: =+V105+20 -> 1273 | X105: =+W105+20 -> 1293 | Y105: =+X105+20 -> 1313 | ... AB105: =+AA105+20 -> 1373
B106: CFFO | O106: -523 | P106: 386 | Q106: 1555 | R106: =+R105+R99 -> 3834.9622 | S106: =+S105+S99 -> 4148.4704 | T106: =+T105+T99 -> 5502.1488 | U106: =+U105+U99 -> 5877.0406 | V106: =+V105+V99 -> 6011.3172 | W106: =+W105+W99 -> 6323.3411 | X106: =+X105+X99 -> 6630.8666 | Y106: =+Y105+Y99 -> 6957.895 | ... AB106: =+AB105+AB99 -> 8051.1544
B107: CapEx | O107: 523 | P107: 1026 | Q107: 1417 | R107: 1500 | S107: =+R107*1.05 -> 1575 | T107: =+S107*1.05 -> 1653.75 | U107: =+T107*1.05 -> 1736.4375 | V107: =+U107*1.05 -> 1823.2594 | W107: =+V107*1.05 -> 1914.4223 | X107: =+W107*1.05 -> 2010.1435 | Y107: =+X107*1.05 -> 2110.6506 | Z107: =+Y107*1.05 -> 2216.1832 | ... AB107: =+AA107*1.05 -> 2443.3419
B108: FCFE | O108: =+O106-O107 -> -1046 | P108: =+P106-P107 -> -640 | Q108: =+Q106-Q107 -> 138 | R108: =+R106-R107 -> 2334.9622 | S108: =+S106-S107 -> 2573.4704 | T108: =+T106-T107 -> 3848.3988 | U108: =+U106-U107 -> 4140.6031 | V108: =+V106-V107 -> 4188.0578 | ... AB108: =+AB106-AB107 -> 5607.8125 | AC108: =+AB108*(1+TR) -> 5663.8906 | AD108: =+AC108*(1+TR) -> 5720.5295 | AE108: =+AD108*(1+TR) -> 5777.7348 | AF108: =+AE108*(1+TR) -> 5835.5121 | AG108: =+AF108*(1+TR) -> 5893.8673 | AH108: =+AG108*(1+TR) -> 5952.8059 | AI108: =+AH108*(1+TR) -> 6012.334 | AJ108: =+AI108*(1+TR) -> 6072.4573 | ... DN108: =+DM108*(1+TR) -> 13731.473
B111: AR-AP | O111: =+O117+O116-O123-O124 -> 11910 | P111: =+P117+P116-P123-P124 -> 16412
B112: Change | P112: =+P111-O111 -> 4502
B114: Cash | E114: 7834 | O114: 5944 | P114: 7067 | Q114: 6553
B115: Securities | E115: =1739+82 -> 1821 | O115: =1124+21 -> 1145 | P115: =1751+57 -> 1808 | Q115: =2185+91 -> 2276
B116: AR (Finance) | E116: =13477+14373 -> 27850 | O116: =10066+12359 -> 22425 | P116: =12147+14067 -> 26214
B117: AR (Trade) | E117: 4329 | O117: 4577 | P117: 5245
B118: Equity | E118: 873 | O118: 1073 | P118: 1051
B119: PP&E | E119: 7835 | O119: 7993 | P119: 7979 | Q119: 8413
B120: Assets | E120: =+SUM(E114:E119) -> 50542 | O120: =+SUM(O114:O119) -> 43157 | P120: =+SUM(P114:P119) -> 49364
...
