Workbook

Sheet Sheet2
C4: Price | D4: 1336
C5: Shares | D5: =+Sheet1!H21 -> 24561
C6: MC | D6: =+D4*D5 -> 32813496
C7: Net Cash | D7: =134136-2656150-399541 -> -2921555
C8: EV | D8: =+D6+D7 -> 29891941

Sheet Sheet1
F2: 2023 | G2: =+F2+1 -> 2024 | H2: =+G2+1 -> 2025 | I2: =+H2+1 -> 2026 | J2: =+I2+1 -> 2027 | K2: =+J2+1 -> 2028 | L2: =+K2+1 -> 2029 | M2: =+L2+1 -> 2030 | N2: =+M2+1 -> 2031 | ... R2: =+Q2+1 -> 2035
B4: SaaS Software | F4: 640182 | G4: 711340 | H4: 740145 | I4: =+H4*1.04 -> 769750.8 | J4: =+I4*1.04 -> 800540.83 | K4: =+J4*1.04 -> 832562.47 | L4: =+K4*1.04 -> 865864.96 | M4: =+L4*1.04 -> 900499.56 | N4: =+M4*1.04 -> 936519.54 | O4: =+N4*1.04 -> 973980.33 | P4: =+O4*1.04 -> 1012939.5 | ... R4: =+Q4*1.04 -> 1095595.4
B5: Professional Services | F5: 99547 | G5: 86536 | H5: 82149 | I5: =+H5*0.95 -> 78041.55 | J5: =+I5*0.95 -> 74139.473 | K5: =+J5*0.95 -> 70432.499 | L5: =+K5*0.95 -> 66910.874 | M5: =+L5*0.95 -> 63565.33 | N5: =+M5*0.95 -> 60387.064 | O5: =+N5*0.95 -> 57367.711 | P5: =+O5*0.95 -> 54499.325 | ... R5: =+Q5*0.95 -> 49185.641
B6: FICO Scores | F6: 773828 | G6: 919650 | H6: 1168575 | I6: =+H6*1.25 -> 1460718.8 | J6: =+I6*1.2 -> 1752862.5 | K6: =+J6*1.18 -> 2068377.8 | L6: =+K6*1.15 -> 2378634.4 | M6: =+L6*1.12 -> 2664070.5 | N6: =+M6*1.12 -> 2983759 | O6: =+N6*1.12 -> 3341810.1 | P6: =+O6*1.12 -> 3742827.3 | Q6: =+P6*1.12 -> 4191966.6 | R6: =+Q6*1.12 -> 4695002.6
B7: Total Revnue | F7: =+SUM(F4:F6) -> 1513557 | G7: =+SUM(G4:G6) -> 1717526 | H7: =+SUM(H4:H6) -> 1990869 | I7: =+SUM(I4:I6) -> 2308511.1 | J7: =+SUM(J4:J6) -> 2627542.8 | K7: =+SUM(K4:K6) -> 2971372.7 | L7: =+SUM(L4:L6) -> 3311410.3 | M7: =+SUM(M4:M6) -> 3628135.4 | ... R7: =+SUM(R4:R6) -> 5839783.6
B8: COGS | F8: 311053 | G8: 348206 | H8: 353722 | I8: =+I7*0.18 -> 415532 | J8: =+J7*0.18 -> 472957.7 | K8: =+K7*0.18 -> 534847.09 | L8: =+L7*0.18 -> 596053.85 | M8: =+M7*0.18 -> 653064.38 | N8: =+N7*0.18 -> 716519.81 | O8: =+O7*0.18 -> 787168.46 | P8: =+P7*0.18 -> 865847.91 | ... R8: =+R7*0.18 -> 1051161
B9: Gross Margin | F9: =+F7-F8 -> 1202504 | G9: =+G7-G8 -> 1369320 | H9: =+H7-H8 -> 1637147 | I9: =+I7-I8 -> 1892979.1 | J9: =+J7-J8 -> 2154585.1 | K9: =+K7-K8 -> 2436525.6 | L9: =+L7-L8 -> 2715356.4 | M9: =+M7-M8 -> 2975071.1 | ... R9: =+R7-R8 -> 4788622.6
B10: R&D | F10: 159950 | G10: 171940 | H10: 188347 | I10: =+H10*(1+I27*0.666666666666667) -> 208380.78 | J10: =+I10*(1+J27*0.666666666666667) -> 227579.32 | K10: =+J10*(1+K27*0.666666666666667) -> 247432.74 | L10: =+K10*(1+L27*0.666666666666667) -> 266309.86 | M10: =+L10*(1+M27*0.666666666666667) -> 283290.95 | N10: =+M10*(1+N27*0.666666666666667) -> 301641.72 | O10: =+N10*(1+O27*0.666666666666667) -> 321469.58 | P10: =+O10*(1+P27*0.666666666666667) -> 342890.7 | ... R10: =+Q10*(1+R27*0.666666666666667) -> 391025.43
B11: S&M | F11: 400565 | G11: 462834 | H11: 513028 | I11: =+I7*0.25 -> 577127.78 | J11: =+J7*0.25 -> 656885.7 | K11: =+K7*0.25 -> 742843.18 | L11: =+L7*0.25 -> 827852.56 | M11: =+M7*0.25 -> 907033.86 | N11: =+N7*0.25 -> 995166.4 | O11: =+O7*0.25 -> 1093289.5 | P11: =+P7*0.25 -> 1202566.5 | ... R11: =+R7*0.25 -> 1459945.9
B12: Amortization | F12: 1100 | G12: 917
B13: Other | F13: -1941 | H13: 10922
B14: Operating Income | F14: =+F9-SUM(F10:F13) -> 642830 | G14: =+G9-SUM(G10:G13) -> 733629 | H14: =+H9-SUM(H10:H13) -> 924850 | I14: =+I9-SUM(I10:I13) -> 1107470.6 | J14: =+J9-SUM(J10:J13) -> 1270120.1 | K14: =+K9-SUM(K10:K13) -> 1446249.7 | L14: =+L9-SUM(L10:L13) -> 1621194 | M14: =+M9-SUM(M10:M13) -> 1784746.2 | ... R14: =+R9-SUM(R10:R13) -> 2937651.2
B15: Interest expenses | F15: 95546 | G15: 105638 | H15: 133647 | I15: 150000 | J15: =+I15*1.08 -> 162000 | K15: =+J15*1.08 -> 174960 | L15: =+K15*1.08 -> 188956.8 | M15: =+L15*1.08 -> 204073.34 | N15: =+M15*1.08 -> 220399.21 | O15: =+N15*1.08 -> 238031.15 | P15: =+O15*1.08 -> 257073.64 | Q15: =+P15*1.08 -> 277639.53 | R15: =+Q15*1.08 -> 299850.69
B16: Other income | F16: 6340 | G16: 14034 | H16: 11392 | I16: 10000 | J16: 10000 | K16: 10000 | L16: 10000 | M16: 10000 | N16: 10000 | O16: 10000 | P16: 10000 | Q16: 10000 | R16: 10000
B17: Pretax | F17: =+F14-F15+F16 -> 553624 | G17: =+G14-G15+G16 -> 642025 | H17: =+H14-H15+H16 -> 802595 | I17: =+I14-I15+I16 -> 967470.55 | J17: =+J14-J15+J16 -> 1118120.1 | K17: =+K14-K15+K16 -> 1281289.7 | L17: =+L14-L15+L16 -> 1442237.2 | M17: =+M14-M15+M16 -> 1590672.9 | ... R17: =+R14-R15+R16 -> 2647800.5
B18: Taxes | F18: 124249 | G18: 129214 | H18: 150649 | I18: =+I17*0.2 -> 193494.11 | J18: =+J17*0.2 -> 223624.02 | K18: =+K17*0.2 -> 256257.94 | L18: =+L17*0.2 -> 288447.44 | M18: =+M17*0.2 -> 318134.58 | N18: =+N17*0.2 -> 351387.69 | O18: =+O17*0.2 -> 388639.88 | P18: =+P17*0.2 -> 430377.47 | ... R18: =+R17*0.2 -> 529560.11
B19: Net Income | F19: =+F17-F18 -> 429375 | G19: =+G17-G18 -> 512811 | H19: =+H17-H18 -> 651946 | I19: =+I17-I18 -> 773976.44 | J19: =+J17-J18 -> 894496.06 | K19: =+K17-K18 -> 1025031.8 | L19: =+L17-L18 -> 1153789.7 | M19: =+M17-M18 -> 1272538.3 | ... R19: =+R17-R18 -> 2118240.4 | S19: =+R19*(1+$U$24) -> 2202970 | T19: =+S19*(1+$U$24) -> 2291088.8 | U19: =+T19*(1+$U$24) -> 2382732.4 | V19: =+U19*(1+$U$24) -> 2478041.7 | W19: =+V19*(1+$U$24) -> 2577163.4 | X19: =+W19*(1+$U$24) -> 2680249.9 | Y19: =+X19*(1+$U$24) -> 2787459.9 | Z19: =+Y19*(1+$U$24) -> 2898958.3 | ... EC19: =+EB19*(1+$U$24) -> 1.9266786e+08
B20: EPS | F20: =+F19/F21 -> 16.926519 | G20: =+G19/G21 -> 20.447825 | H20: =+H19/H21 -> 26.543952 | I20: =+I19/I21 -> 31.512416 | J20: =+J19/J21 -> 36.419367 | K20: =+K19/K21 -> 41.734122 | L20: =+L19/L21 -> 46.976497 | M20: =+M19/M21 -> 51.81134 | ... R20: =+R19/R21 -> 86.244063
B21: Shares | F21: 25367 | G21: 25079 | H21: 24561 | I21: =+H21+0 -> 24561 | J21: =+I21+0 -> 24561 | K21: =+J21+0 -> 24561 | L21: =+K21+0 -> 24561 | M21: =+L21+0 -> 24561 | N21: =+M21+0 -> 24561 | O21: =+N21+0 -> 24561 | P21: =+O21+0 -> 24561 | ... R21: =+Q21+0 -> 24561
B23: Gross Margin | F23: =+F9/F7 -> 0.79448874 | G23: =+G9/G7 -> 0.79726304 | H23: =+H9/H7 -> 0.82232784 | I23: =+I9/I7 -> 0.82 | J23: =+J9/J7 -> 0.82 | K23: =+K9/K7 -> 0.82 | L23: =+L9/L7 -> 0.82 | M23: =+M9/M7 -> 0.82 | ... R23: =+R9/R7 -> 0.82 | T23: Discount | U23: 0.1
B24: Operating Margin | F24: =+F14/F7 -> 0.42471476 | G24: =+G14/G7 -> 0.42714288 | H24: =+H14/H7 -> 0.46454588 | I24: =+I14/I7 -> 0.47973369 | J24: =+J14/J7 -> 0.48338702 | K24: =+K14/K7 -> 0.4867278 | L24: =+L14/L7 -> 0.48957811 | M24: =+M14/M7 -> 0.49191831 | ... R24: =+R14/R7 -> 0.50304111 | T24: Terminal | U24: 0.04
B25: Net Margin | F25: =+F19/F7 -> 0.28368605 | G25: =+G19/G7 -> 0.29857539 | H25: =+H19/H7 -> 0.32746806 | I25: =+I19/I7 -> 0.33527083 | J25: =+J19/J7 -> 0.34043063 | K25: =+K19/K7 -> 0.3449691 | L25: =+L19/L7 -> 0.34842851 | M25: =+M19/M7 -> 0.35074168 | ... R25: =+R19/R7 -> 0.36272584 | T25: NPV | U25: =NPV(U23,I33:EJ33) -> 25069933
T26: Net Cash | U26: =+Sheet2!D7 -> -2921555
B27: Revenue Y/Y | G27: =+G7/F7 -1 -> 0.13476136 | H27: =+H7/G7 -1 -> 0.15914926 | I27: =+I7/H7 -1 -> 0.15954947 | J27: =+J7/I7 -1 -> 0.13819804 | K27: =+K7/J7 -1 -> 0.13085606 | L27: =+L7/K7 -1 -> 0.11443786 | M27: =+M7/L7 -1 -> 0.095646616 | N27: =+N7/M7 -1 -> 0.097165662 | ... R27: =+R7/Q7 -1 -> 0.10242878 | T27: Value | U27: =+U25+U26 -> 22148378
B28: SaaS Y/Y | G28: =+G4/F4 -1 -> 0.11115277 | H28: =+H4/G4 -1 -> 0.040493997 | I28: =+I4/H4 -1 -> 0.04 | J28: =+J4/I4 -1 -> 0.04 | K28: =+K4/J4 -1 -> 0.04 | L28: =+L4/K4 -1 -> 0.04 | M28: =+M4/L4 -1 -> 0.04 | N28: =+N4/M4 -1 -> 0.04 | ... R28: =+R4/Q4 -1 -> 0.04 | T28: Price | U28: =+U27/R21 -> 901.77019
B29: Score Y/Y | G29: =+G6/F6 -1 -> 0.18844239 | H29: =+H6/G6 -1 -> 0.27067363 | I29: =+I6/H6 -1 -> 0.25 | J29: =+J6/I6 -1 -> 0.2 | K29: =+K6/J6 -1 -> 0.18 | L29: =+L6/K6 -1 -> 0.15 | M29: =+M6/L6 -1 -> 0.12 | N29: =+N6/M6 -1 -> 0.12 | ... R29: =+R6/Q6 -1 -> 0.12 | T29: Diff | U29: =+U28/Sheet2!D4 -1 -> -0.32502231
B31: CFFO | F31: 468915 | G31: 632964 | H31: 778807 | I31: =+I19+I15 -> 923976.44 | J31: =+J19+J15 -> 1056496.1 | K31: =+K19+K15 -> 1199991.8 | L31: =+L19+L15 -> 1342746.5 | M31: =+M19+M15 -> 1476611.7 | N31: =+N19+N15 -> 1625950 | O31: =+O19+O15 -> 1792590.7 | P31: =+P19+P15 -> 1978583.5 | ... R31: =+R19+R15 -> 2418091.1
B32: CapEx | F32: 4237 | G32: 8884 | H32: 8922 | I32: =+H32*1.02 -> 9100.44 | J32: =+I32*1.02 -> 9282.4488 | K32: =+J32*1.02 -> 9468.0978 | L32: =+K32*1.02 -> 9657.4597 | M32: =+L32*1.02 -> 9850.6089 | N32: =+M32*1.02 -> 10047.621 | O32: =+N32*1.02 -> 10248.574 | P32: =+O32*1.02 -> 10453.545 | ... R32: =+Q32*1.02 -> 10875.868
B33: FCFF | F33: =+F31-F32 -> 464678 | G33: =+G31-G32 -> 624080 | H33: =+H31-H32 -> 769885 | I33: =+I31-I32 -> 914876 | J33: =+J31-J32 -> 1047213.6 | K33: =+K31-K32 -> 1190523.7 | L33: =+L31-L32 -> 1333089.1 | M33: =+M31-M32 -> 1466761.1 | ... R33: =+R31-R32 -> 2407215.3 | S33: =+R33*(1+$U$24) -> 2503503.9 | T33: =+S33*(1+$U$24) -> 2603644 | U33: =+T33*(1+$U$24) -> 2707789.8 | V33: =+U33*(1+$U$24) -> 2816101.4 | W33: =+V33*(1+$U$24) -> 2928745.4 | X33: =+W33*(1+$U$24) -> 3045895.2 | Y33: =+X33*(1+$U$24) -> 3167731.1 | Z33: =+Y33*(1+$U$24) -> 3294440.3 | ... EC33: =+EB33*(1+$U$24) -> 2.1895201e+08
B34: SBC | F34: 123847 | G34: 149439 | H34: 156667
B35: Adj. FCF | F35: =+F33-F34 -> 340831 | G35: =+G33-G34 -> 474641 | H35: =+H33-H34 -> 613218
B37: Stock Buybacks | F37: 405526 | G37: 821702 | H37: 1414502
B38: Net Stock Buybacks | F38: =+F37-F34 -> 281679 | G38: =+G37-G34 -> 672263 | H38: =+H37-H34 -> 1257835
B39: Buyback yield | F39: =+F38/Sheet2!$D$8 -> 0.0094232422 | G39: =+G38/Sheet2!$D$8 -> 0.022489774 | H39: =+H38/Sheet2!$D$8 -> 0.042079402
B40: Buyback Ratio
B42: R&D | F42: =+F10/F$7 -> 0.10567821 | G42: =+G10/G$7 -> 0.10010911 | H42: =+H10/H$7 -> 0.094605421
B43: S&M | F43: =+F11/F$7 -> 0.26465141 | G43: =+G11/G$7 -> 0.26947714 | H43: =+H11/H$7 -> 0.25769049
