Workbook
Name MV: Sheet2!$AD$21

Sheet Sheet1
D4: Price | E4: 230 | G4: Upside | H4: =+Sheet2!AD23/Sheet1!E4 -1 -> 0.50912286
D5: Shares | E5: 43.304
D6: Cap | E6: =+E4*E5 -> 9959.92
D7: Net Cash | E7: =334+1039-706-215 -> 452
D8: EV | E8: =+E6-E7 -> 9507.92
E11: =+E8/Sheet2!T18 -> 13.983225

Sheet Sheet2
C1: Q121 | D1: Q221 | E1: Q321 | F1: Q421 | G1: Q122 | H1: Q222 | I1: Q322 | J1: Q422 | O1: FY18 | P1: FY19 | Q1: FY20 | R1: FY21 | S1: FY22 | T1: FY23 | U1: FY24 | V1: FY25 | W1: FY26 | X1: FY27 | Y1: FY28 | Z1: FY29 | AA1: FY30
B4: Revenue | C4: 1353 | D4: 2582 | G4: 1409 | H4: 2674 | O4: 6192 | P4: 6491 | Q4: 5547 | R4: 5775 | S4: 6410 | T4: =+S4*1.15 -> 7371.5 | U4: =+T4*1.15 -> 8477.225 | V4: =+U4*1.15 -> 9748.8087 | W4: =+V4*1.12 -> 10918.666 | X4: =+W4*1.05 -> 11464.599 | Y4: =+X4*1.05 -> 12037.829 | Z4: =+Y4*1.05 -> 12639.72 | AA4: =+Z4*1.05 -> 13271.707
B5: Other Income | C5: 21 | G5: 29 | H5: 206 | O5: 179 | P5: 186 | Q5: 114 | R5: 134 | S5: =153+221 -> 374 | T5: =+S5*1.01 -> 377.74 | U5: =+T5*1.01 -> 381.5174 | V5: =+U5*1.01 -> 385.33257 | W5: =+V5*1.01 -> 389.1859 | X5: =+W5*1.01 -> 393.07776 | Y5: =+X5*1.01 -> 397.00854 | Z5: =+Y5*1.01 -> 400.97862 | AA5: =+Z5*1.01 -> 404.98841
B6: COGS | C6: 665 | G6: 684 | O6: 3209 | P6: 3444 | Q6: 2792 | R6: 2745 | S6: 3183 | T6: =+T4*0.5 -> 3685.75 | U6: =+U4*0.5 -> 4238.6125 | V6: =+V4*0.5 -> 4874.4044 | W6: =+W4*0.5 -> 5459.3329 | X6: =+X4*0.5 -> 5732.2995 | Y6: =+Y4*0.5 -> 6018.9145 | Z6: =+Z4*0.5 -> 6319.8602 | AA6: =+AA4*0.5 -> 6635.8533
B7: Gross Profit | C7: =+C5+C4-C6 -> 709 | D7: =+D5+D4-D6 -> 2582 | E7: =+E5+E4-E6 -> 0 | F7: =+F5+F4-F6 -> 0 | G7: =+G5+G4-G6 -> 754 | H7: =+H5+H4-H6 -> 2880 | I7: =+I5+I4-I6 -> 0 | J7: =+J5+J4-J6 -> 0 | O7: =+O5+O4-O6 -> 3162 | P7: =+P5+P4-P6 -> 3233 | Q7: =+Q5+Q4-Q6 -> 2869 | R7: =+R5+R4-R6 -> 3164 | S7: =+S5+S4-S6 -> 3601 | T7: =+T5+T4-T6 -> 4063.49 | U7: =+U5+U4-U6 -> 4620.1299 | V7: =+V5+V4-V6 -> 5259.7369 | ... AA7: =+AA5+AA4-AA6 -> 7040.8417
B8: G&A | C8: 414 | G8: 457 | O8: 1574 | P8: 1678 | Q8: 1537 | R8: 1643 | S8: 1836 | T8: =+T4*0.285 -> 2100.8775 | U8: =+U4*0.285 -> 2416.0091 | V8: =+V4*0.285 -> 2778.4105 | W8: =+W4*0.285 -> 3111.8198 | X8: =+X4*0.285 -> 3267.4107 | Y8: =+Y4*0.285 -> 3430.7813 | Z8: =+Z4*0.285 -> 3602.3203 | AA8: =+AA4*0.285 -> 3782.4364
B9: D&A | C9: 58 | G9: 60 | O9: 318 | P9: 280 | Q9: 282 | R9: 251 | S9: 249 | T9: =+S9*1.05 -> 261.45 | U9: =+T9*1.05 -> 274.5225 | V9: =+U9*1.05 -> 288.24863 | W9: =+V9*1.05 -> 302.66106 | X9: =+W9*1.05 -> 317.79411 | Y9: =+X9*1.05 -> 333.68381 | Z9: =+Y9*1.05 -> 350.36801 | AA9: =+Z9*1.05 -> 367.88641
B10: Other Expenses | C10: 149 | G10: 153 | O10: 775 | P10: 781 | Q10: 642 | R10: 656 | S10: 768 | T10: =+S10*0.98 -> 752.64 | U10: =+T10*0.98 -> 737.5872 | V10: =+U10*0.98 -> 722.83546 | W10: =+V10*0.98 -> 708.37875 | X10: =+W10*0.98 -> 694.21117 | Y10: =+X10*0.98 -> 680.32695 | Z10: =+Y10*0.98 -> 666.72041 | AA10: =+Z10*0.98 -> 653.386
B11: Equity Income | C11: 7 | G11: 17 | O11: 37 | P11: 37 | Q11: 13 | R11: 11 | S11: 32 | T11: =+S11*0.8 -> 25.6 | U11: =+T11*0.8 -> 20.48 | V11: =+U11*0.8 -> 16.384 | W11: =+V11*0.8 -> 13.1072 | X11: =+W11*0.8 -> 10.48576 | Y11: =+X11*0.8 -> 8.388608 | Z11: =+Y11*0.8 -> 6.7108864 | AA11: =+Z11*0.8 -> 5.3687091
B12: Other Income | C12: -10 | G12: -20 | O12: -13 | P12: -20 | Q12: -24 | R12: -17 | S12: -48 | T12: =+S12*0.99 -> -47.52 | U12: =+T12*0.99 -> -47.0448 | V12: =+U12*0.99 -> -46.574352 | W12: =+V12*0.99 -> -46.108608 | X12: =+W12*0.99 -> -45.647522 | Y12: =+X12*0.99 -> -45.191047 | Z12: =+Y12*0.99 -> -44.739137 | AA12: =+Z12*0.99 -> -44.291745
B13: EBIT | C13: =+C7-C8-C9-C10+C11+C12 -> 85 | D13: =+D7-D8-D9-D10+D11+D12 -> 2582 | E13: =+E7-E8-E9-E10+E11+E12 -> 0 | F13: =+F7-F8-F9-F10+F11+F12 -> 0 | G13: =+G7-G8-G9-G10+G11+G12 -> 81 | H13: =+H7-H8-H9-H10+H11+H12 -> 2880 | I13: =+I7-I8-I9-I10+I11+I12 -> 0 | J13: =+J7-J8-J9-J10+J11+J12 -> 0 | O13: =+O7-O8-O9-O10+O11+O12 -> 519 | P13: =+P7-P8-P9-P10+P11+P12 -> 511 | Q13: =+Q7-Q8-Q9-Q10+Q11+Q12 -> 397 | R13: =+R7-R8-R9-R10+R11+R12 -> 608 | S13: =+S7-S8-S9-S10+S11+S12 -> 732 | T13: =+T7-T8-T9-T10+T11+T12 -> 926.6025 | U13: =+U7-U8-U9-U10+U11+U12 -> 1165.4463 | V13: =+V7-V8-V9-V10+V11+V12 -> 1440.052 | ... AA13: =+AA7-AA8-AA9-AA10+AA11+AA12 -> 2198.2099
B14: Interest Income | C14: 2 | G14: 1 | O14: 6 | P14: 11 | Q14: 9 | R14: 4 | S14: 12 | T14: =+S14 -> 12 | U14: =+T14 -> 12 | V14: =+U14 -> 12 | W14: =+V14 -> 12 | X14: =+W14 -> 12 | Y14: =+X14 -> 12 | Z14: =+Y14 -> 12 | AA14: =+Z14 -> 12
B15: Interest Expense | C15: 11 | G15: 8 | O15: 39 | P15: 46 | Q15: 40 | R15: 31 | S15: 32 | T15: =+S15 -> 32 | U15: =+T15 -> 32 | V15: =+U15 -> 32 | W15: =+V15 -> 32 | X15: =+W15 -> 32 | Y15: =+X15 -> 32 | Z15: =+Y15 -> 32 | AA15: =+Z15 -> 32
B16: EBT | C16: =+C13+C14-C15 -> 76 | D16: =+D13+D14-D15 -> 2582 | E16: =+E13+E14-E15 -> 0 | F16: =+F13+F14-F15 -> 0 | G16: =+G13+G14-G15 -> 74 | H16: =+H13+H14-H15 -> 2880 | I16: =+I13+I14-I15 -> 0 | J16: =+J13+J14-J15 -> 0 | O16: =+O13+O14-O15 -> 486 | P16: =+P13+P14-P15 -> 476 | Q16: =+Q13+Q14-Q15 -> 366 | R16: =+R13+R14-R15 -> 581 | S16: =+S13+S14-S15 -> 712 | T16: =+T13+T14-T15 -> 906.6025 | U16: =+U13+U14-U15 -> 1145.4463 | V16: =+V13+V14-V15 -> 1420.052 | ... AA16: =+AA13+AA14-AA15 -> 2178.2099
B17: Taxes | C17: 21 | G17: 15 | O17: 131 | P17: 123 | Q17: 83 | R17: 150 | S17: 183 | T17: =+T16*0.25 -> 226.65062 | U17: =+U16*0.25 -> 286.36157 | V17: =+V16*0.25 -> 355.01301 | W17: =+W16*0.25 -> 418.16446 | X17: =+X16*0.25 -> 447.69988 | Y17: =+Y16*0.25 -> 478.58214 | Z17: =+Z16*0.25 -> 510.85047 | AA17: =+AA16*0.25 -> 544.55247
B18: Net Income | C18: =+C16-C17 -> 55 | D18: =+D16-D17 -> 2582 | E18: =+E16-E17 -> 0 | F18: =+F16-F17 -> 0 | G18: =+G16-G17 -> 59 | H18: =+H16-H17 -> 2880 | I18: =+I16-I17 -> 0 | J18: =+J16-J17 -> 0 | O18: =+O16-O17 -> 355 | P18: =+P16-P17 -> 353 | Q18: =+Q16-Q17 -> 283 | R18: =+R16-R17 -> 431 | S18: =+S16-S17 -> 529 | T18: =+T16-T17 -> 679.95187 | U18: =+U16-U17 -> 859.08471 | V18: =+V16-V17 -> 1065.039 | ... AA18: =+AA16-AA17 -> 1633.6574 | AB18: =+AA18*(1+MV) -> 1682.6671 | AC18: =+AB18*(1+MV) -> 1733.1471 | AD18: =+AC18*(1+MV) -> 1785.1415 | AE18: =+AD18*(1+MV) -> 1838.6958 | AF18: =+AE18*(1+MV) -> 1893.8567 | AG18: =+AF18*(1+MV) -> 1950.6724 | AH18: =+AG18*(1+MV) -> 2009.1925 | AI18: =+AH18*(1+MV) -> 2069.4683 | ... DD18: =+DC18*(1+MV) -> 17905.077
B20: Gross Margin | C20: =+C7/C4 -> 0.52402069 | G20: =+G7/G4 -> 0.5351313 | O20: =+O7/O4 -> 0.51065891 | P20: =+P7/P4 -> 0.49807426 | Q20: =+Q7/Q4 -> 0.51721651 | R20: =+R7/R4 -> 0.54787879 | S20: =+S7/S4 -> 0.56177847 | T20: =+T7/T4 -> 0.5512433 | U20: =+U7/U4 -> 0.54500499 | V20: =+V7/V4 -> 0.53952612 | ... AA20: =+AA7/AA4 -> 0.53051517 | AC20: Discount | AD20: 0.1
B21: EBIT Margin | C21: =+C13/C4 -> 0.062823356 | G21: =+G13/G4 -> 0.05748758 | O21: =+O13/O4 -> 0.083817829 | P21: =+P13/P4 -> 0.078724388 | Q21: =+Q13/Q4 -> 0.071570218 | R21: =+R13/R4 -> 0.10528139 | S21: =+S13/S4 -> 0.11419657 | T21: =+T13/T4 -> 0.12570067 | U21: =+U13/U4 -> 0.13747969 | V21: =+V13/V4 -> 0.14771569 | ... AA21: =+AA13/AA4 -> 0.16563129 | AC21: Maturity | AD21: 0.03
B22: Net Margin | C22: =+C18/C4 -> 0.040650407 | G22: =+G18/G4 -> 0.041873669 | O22: =+O18/O4 -> 0.057332041 | P22: =+P18/P4 -> 0.054382992 | Q22: =+Q18/Q4 -> 0.051018569 | R22: =+R18/R4 -> 0.074632035 | S22: =+S18/S4 -> 0.082527301 | T22: =+T18/T4 -> 0.09224064 | U22: =+U18/U4 -> 0.10134032 | V22: =+V18/V4 -> 0.10924812 | ... AA22: =+AA18/AA4 -> 0.12309324 | AC22: NPV | AD22: =NPV(AD20,S30:EE30) -> 15030.743
AC23: Price | AD23: =+AD22/Sheet1!E5 -> 347.09826
B24: Revenue Y/Y | G24: =+G4/C4 -1 -> 0.041389505 | P24: =+P4/O4 -1 -> 0.048288114 | Q24: =+Q4/P4 -1 -> -0.14543214 | R24: =+R4/Q4 -1 -> 0.041103299 | S24: =+S4/R4 -1 -> 0.10995671 | T24: =+T4/S4 -1 -> 0.15 | U24: =+U4/T4 -1 -> 0.15 | V24: =+V4/U4 -1 -> 0.15 | W24: =+W4/V4 -1 -> 0.12 | ... AA24: =+AA4/Z4 -1 -> 0.05
B25: G&A Y/Y | G25: =+G8/C8 -1 -> 0.10386473 | P25: =+P8/O8 -1 -> 0.066073698 | Q25: =+Q8/P8 -1 -> -0.084028605 | R25: =+R8/Q8 -1 -> 0.068965517 | S25: =+S8/R8 -1 -> 0.11746805 | T25: =+T8/S8 -1 -> 0.14426879 | U25: =+U8/T8 -1 -> 0.15 | V25: =+V8/U8 -1 -> 0.15 | W25: =+W8/V8 -1 -> 0.12 | ... AA25: =+AA8/Z8 -1 -> 0.05
AC26: P/E FY25 | AD26: =+Sheet1!E6/Sheet2!V18 -> 9.351695
AC27: P/E FY30 | AD27: =+Sheet1!E6/Sheet2!AA18 -> 6.0967006
B28: CFFO | R28: 690 | S28: 174 | T28: =+T18+T9 -> 941.40187 | U28: =+U18+U9 -> 1133.6072 | V28: =+V18+V9 -> 1353.2876 | W28: =+W18+W9 -> 1557.1544 | X28: =+X18+X9 -> 1660.8937 | Y28: =+Y18+Y9 -> 1769.4302 | Z28: =+Z18+Z9 -> 1882.9194 | AA28: =+AA18+AA9 -> 2001.5438
B29: CapEx | R29: 271 | S29: 349 | T29: =+S29*1.02 -> 355.98 | U29: =+T29*1.02 -> 363.0996 | V29: =+U29*1.02 -> 370.36159 | W29: =+V29*1.02 -> 377.76882 | X29: =+W29*1.02 -> 385.3242 | Y29: =+X29*1.02 -> 393.03068 | Z29: =+Y29*1.02 -> 400.8913 | AA29: =+Z29*1.02 -> 408.90912
B30: FCF | R30: =+R28-R29 -> 419 | S30: =+S28-S29 -> -175 | T30: =+T28-T29 -> 585.42187 | U30: =+U28-U29 -> 770.50761 | V30: =+V28-V29 -> 982.92605 | W30: =+W28-W29 -> 1179.3856 | X30: =+X28-X29 -> 1275.5695 | Y30: =+Y28-Y29 -> 1376.3996 | ... AA30: =+AA28-AA29 -> 1592.6347 | AB30: =+AA30*(1+MV) -> 1640.4137 | AC30: =+AB30*(1+MV) -> 1689.6261 | AD30: =+AC30*(1+MV) -> 1740.3149 | AE30: =+AD30*(1+MV) -> 1792.5244 | AF30: =+AE30*(1+MV) -> 1846.3001 | AG30: =+AF30*(1+MV) -> 1901.6891 | AH30: =+AG30*(1+MV) -> 1958.7398 | AI30: =+AH30*(1+MV) -> 2017.502 | ... EZ30: =+EY30*(1+MV) -> 72130.369
