Workbook
Name TR: Model!$AH$35

Sheet Sheet1
C1: Q122 | D1: Q222 | E1: Q322 | F1: Q422
B2: Segments: | J2: Outlook:
A3: exp growth | J3: FY23
A4: 10-13% | B4: Aerospace: | J4: Sales | K4: 72-73bn
B5: Revenue | C5: 4824 | D5: 5011 | E5: 5100 | F5: 5662 | J5: EPS | K5: 4,9-5,05
B6: Profit | C6: 584 | D6: 546 | E6: 616 | F6: 741 | J6: FCF | K6: 4,8bn
B7: Margin | C7: =+C6/C5 -> 0.12106136 | D7: =+D6/D5 -> 0.10896029 | E7: =+E6/E5 -> 0.12078431 | F7: =+F6/F5 -> 0.13087248
J8: Labor costs are a burden
A9: 12-16% | B9: Pratt&Whitney | J9: Flight Market is important
B10: Revenue | C10: 4529 | D10: 4969 | E10: 5380 | F10: 5652
B11: Profit | C11: 308 | D11: 302 | E11: 316 | F11: 306 | J11: Digitilization, Automation in the factory#
B12: Margin | C12: =+C11/C10 -> 0.068006182 | D12: =+D11/D10 -> 0.060776816 | E12: =+E11/E10 -> 0.058736059 | F12: =+F11/F10 -> 0.054140127 | J12: driving margin imporvement
A14: 0 | B14: Raytheon Intelligence & Space
B15: Revenue | C15: 3572 | D15: 3570 | E15: 3626 | F15: 3544 | J15: Orderbook of 175bn
B16: Profit | C16: 378 | D16: 315 | E16: 371 | F16: 278 | J16: 70bn within defense
B17: Margin | C17: =+C16/C15 -> 0.10582307 | D17: =+D16/D15 -> 0.088235294 | E17: =+E16/E15 -> 0.1023166 | F17: =+F16/F15 -> 0.078442438
A19: 3-6% | B19: Raytheon Missiles & Defense
B20: Revenue | C20: 3527 | D20: 3558 | E20: 3678 | F20: 4100
B21: Profit | C21: 387 | D21: 348 | E21: 408 | F21: 376
B22: Margin | C22: =+C21/C20 -> 0.10972498 | D22: =+D21/D20 -> 0.097807757 | E22: =+E21/E20 -> 0.11092985 | F22: =+F21/F20 -> 0.091707317

Sheet Model
D1: Q121 | E1: Q221 | F1: Q321 | G1: Q421 | H1: Q122 | I1: Q222 | J1: Q322 | K1: Q422 | L1: Q123 | M1: Q223 | N1: Q323 | O1: Q423 | U1: 2020 | V1: =+U1+1 -> 2021 | W1: =+V1+1 -> 2022 | X1: =+W1+1 -> 2023 | Y1: =+X1+1 -> 2024 | Z1: =+Y1+1 -> 2025 | AA1: =+Z1+1 -> 2026 | AB1: =+AA1+1 -> 2027 | AC1: =+AB1+1 -> 2028 | ... AE1: =+AD1+1 -> 2030
B3: =+W3/W10 -> 0.30707875 | C3: Aerospace | H3: =+Sheet1!C5 -> 4824 | I3: =+Sheet1!D5 -> 5011 | J3: =+Sheet1!E5 -> 5100 | K3: 5662 | W3: =+SUM(H3:K3) -> 20597
B4: =+W4/W10 -> 0.30607985 | C4: Ratt&Whitney | H4: =+Sheet1!C10 -> 4529 | I4: =+Sheet1!D10 -> 4969 | J4: =+Sheet1!E10 -> 5380 | K4: 5652 | W4: =+SUM(H4:K4) -> 20530
B5: =+W5/W10 -> 0.21337627 | C5: Intel&Space | H5: =+Sheet1!C15 -> 3572 | I5: =+Sheet1!D15 -> 3570 | J5: =+Sheet1!E15 -> 3626 | K5: 3544 | W5: =+SUM(H5:K5) -> 14312
B6: =+W6/W10 -> 0.22159108 | C6: Missile&Defense | H6: =+Sheet1!C20 -> 3527 | I6: =+Sheet1!D20 -> 3558 | J6: =+Sheet1!E20 -> 3678 | K6: 4100 | W6: =+SUM(H6:K6) -> 14863
C8: Product Sales | D8: 11664 | E8: 12179 | F8: 12331 | G8: =+V8-F8-E8-D8 -> 13096 | H8: 11862 | I8: 12258 | J8: 12756 | K8: =+W8-J8-I8-H8 -> 13897 | L8: 12787 | M8: 13411 | U8: 43319 | V8: 49270 | W8: 50773 | X8: =+(M8+L8)*2 -> 52396 | Y8: =+X8*1.06 -> 55539.76 | Z8: =+Y8*1.06 -> 58872.146 | AA8: =+Z8*1.06 -> 62404.474 | AB8: =+AA8*1.06 -> 66148.743 | AC8: =+AB8*1.06 -> 70117.667 | AD8: =+AC8*1.05 -> 73623.551 | AE8: =+AD8*1.05 -> 77304.728
C9: Service Sales | D9: 3587 | E9: 3701 | F9: 3882 | G9: =+V9-F9-E9-D9 -> 3948 | H9: 3854 | I9: 4056 | J9: 4195 | K9: =+W9-J9-I9-H9 -> 4196 | L9: 4427 | M9: 4904 | U9: 13268 | V9: 15118 | W9: 16301 | X9: =+(M9+L9)*2 -> 18662 | Y9: =+X9*1.08 -> 20154.96 | Z9: =+Y9*1.08 -> 21767.357 | AA9: =+Z9*1.08 -> 23508.745 | AB9: =+AA9*1.08 -> 25389.445 | AC9: =+AB9*1.08 -> 27420.601 | AD9: =+AC9*1.06 -> 29065.837 | AE9: =+AD9*1.06 -> 30809.787
C10: Revenue | D10: =+D8+D9 -> 15251 | E10: =+E8+E9 -> 15880 | F10: =+F8+F9 -> 16213 | G10: =+G8+G9 -> 17044 | H10: =+H8+H9 -> 15716 | I10: =+I8+I9 -> 16314 | J10: =+J8+J9 -> 16951 | K10: =+K8+K9 -> 18093 | ... M10: =+M8+M9 -> 18315 | U10: =+U8+U9 -> 56587 | V10: =+V8+V9 -> 64388 | W10: =+W8+W9 -> 67074 | X10: =+X8+X9 -> 71058 | Y10: =+Y8+Y9 -> 75694.72 | Z10: =+Z8+Z9 -> 80639.502 | AA10: =+AA8+AA9 -> 85913.22 | AB10: =+AB8+AB9 -> 91538.188 | ... AE10: =+AE8+AE9 -> 108114.52
C11: Product Cost | D11: 9974 | E11: 9997 | F11: 10296 | G11: =+V11-F11-E11-D11 -> 10828 | H11: 9820 | I11: 10040 | J11: 10493 | K11: =+W11-J11-I11-H11 -> 11574 | L11: 10700 | M11: 11089 | U11: 38137 | V11: 41095 | W11: 41927 | X11: =+(M11+L11)*2 -> 43578 | Y11: =+Y8*0.83 -> 46098.001 | Z11: =+Z8*0.83 -> 48863.881 | AA11: =+AA8*0.83 -> 51795.714 | AB11: =+AB8*0.83 -> 54903.457 | AC11: =+AC8*0.83 -> 58197.664 | AD11: =+AD8*0.83 -> 61107.547 | AE11: =+AE8*0.83 -> 64162.924
C12: Service Cost | D12: 2563 | E12: 2658 | F12: 2793 | G12: =+V12-F12-E12-D12 -> 2788 | H12: 2740 | I12: 2816 | J12: 2971 | K12: =+W12-J12-I12-H12 -> 2952 | L12: 2945 | M12: 3429 | U12: 9919 | V12: 10802 | W12: 11479 | X12: =+(M12+L12)*2 -> 12748 | Y12: =+Y9*0.7 -> 14108.472 | Z12: =+Z9*0.7 -> 15237.15 | AA12: =+AA9*0.7 -> 16456.122 | AB12: =+AB9*0.7 -> 17772.611 | AC12: =+AC9*0.7 -> 19194.42 | AD12: =+AD9*0.7 -> 20346.086 | AE12: =+AE9*0.7 -> 21566.851
C13: COGS | D13: =+D11+D12 -> 12537 | E13: =+E11+E12 -> 12655 | F13: =+F11+F12 -> 13089 | G13: =+G11+G12 -> 13616 | H13: =+H11+H12 -> 12560 | I13: =+I11+I12 -> 12856 | J13: =+J11+J12 -> 13464 | K13: =+K11+K12 -> 14526 | ... M13: =+M11+M12 -> 14518 | U13: =+U11+U12 -> 48056 | V13: =+V11+V12 -> 51897 | W13: =+W11+W12 -> 53406 | X13: =+X11+X12 -> 56326 | Y13: =+Y11+Y12 -> 60206.473 | Z13: =+Z11+Z12 -> 64101.031 | AA13: =+AA11+AA12 -> 68251.835 | AB13: =+AB11+AB12 -> 72676.068 | ... AE13: =+AE11+AE12 -> 85729.775
C14: Gross Profit | D14: =+D10-D13 -> 2714 | E14: =+E10-E13 -> 3225 | F14: =+F10-F13 -> 3124 | G14: =+G10-G13 -> 3428 | H14: =+H10-H13 -> 3156 | I14: =+I10-I13 -> 3458 | J14: =+J10-J13 -> 3487 | K14: =+K10-K13 -> 3567 | ... M14: =+M10-M13 -> 3797 | U14: =+U10-U13 -> 8531 | V14: =+V10-V13 -> 12491 | W14: =+W10-W13 -> 13668 | X14: =+X10-X13 -> 14732 | Y14: =+Y10-Y13 -> 15488.247 | Z14: =+Z10-Z13 -> 16538.472 | AA14: =+AA10-AA13 -> 17661.384 | AB14: =+AB10-AB13 -> 18862.12 | ... AE14: =+AE10-AE13 -> 22384.74
C15: R&D | D15: 589 | E15: 657 | F15: 676 | G15: =+V15-F15-E15-D15 -> 810 | H15: 635 | I15: 698 | J15: 662 | K15: =+W15-J15-I15-H15 -> 716 | L15: 607 | M15: 729 | U15: 2581 | V15: 2732 | W15: 2711 | X15: =+(M15+L15)*2 -> 2672 | Y15: =+X15*1.02 -> 2725.44 | Z15: =+Y15*1.02 -> 2779.9488 | AA15: =+Z15*1.03 -> 2863.3473 | AB15: =+AA15*1.03 -> 2949.2477 | AC15: =+AB15*1.03 -> 3037.7251 | AD15: =+AC15*1.03 -> 3128.8569 | AE15: =+AD15*1.03 -> 3222.7226
C16: SG&A | D16: 1220 | E16: 1368 | F16: 1229 | G16: =+V16-F16-E16-D16 -> 1407 | H16: 1469 | I16: 1424 | J16: 1391 | K16: =+W16-J16-I16-H16 -> 1379 | L16: 1398 | M16: 1635 | U16: 5540 | V16: 5224 | W16: 5663 | X16: =+(M16+L16)*2 -> 6066 | Y16: =+X16*1.04 -> 6308.64 | Z16: =+Y16*1.03 -> 6497.8992 | AA16: =+Z16*1.02 -> 6627.8572 | AB16: =+AA16*1.02 -> 6760.4143 | AC16: =+AB16*1.01 -> 6828.0185 | AD16: =+AC16*1.01 -> 6896.2987 | AE16: =+AD16*1.01 -> 6965.2616
C17: Operating Expense | D17: =+D15+D16 -> 1809 | E17: =+E15+E16 -> 2025 | F17: =+F15+F16 -> 1905 | G17: =+G15+G16 -> 2217 | H17: =+H15+H16 -> 2104 | I17: =+I15+I16 -> 2122 | J17: =+J15+J16 -> 2053 | K17: =+K15+K16 -> 2095 | ... M17: =+M15+M16 -> 2364 | U17: =+U15+U16 -> 8121 | V17: =+V15+V16 -> 7956 | W17: =+W15+W16 -> 8374 | X17: =+(M17+L17)*2 -> 8738 | Y17: =+Y15+Y16 -> 9034.08 | Z17: =+Z15+Z16 -> 9277.848 | AA17: =+AA15+AA16 -> 9491.2044 | AB17: =+AB15+AB16 -> 9709.662 | AC17: =+AC15+AC16 -> 9865.7436 | AD17: =+AD15+AD16 -> 10025.156 | AE17: =+AE15+AE16 -> 10187.984
C18: Operating Income | D18: =+D14-D17 -> 905 | E18: =+E14-E17 -> 1200 | F18: =+F14-F17 -> 1219 | G18: =+G14-G17 -> 1211 | H18: =+H14-H17 -> 1052 | I18: =+I14-I17 -> 1336 | J18: =+J14-J17 -> 1434 | K18: =+K14-K17 -> 1472 | ... M18: =+M14-M17 -> 1433 | U18: =+U14-U17 -> 410 | V18: =+V14-V17 -> 4535 | W18: =+W14-W17 -> 5294 | X18: =+X14-X17 -> 5994 | Y18: =+Y14-Y17 -> 6454.1672 | Z18: =+Z14-Z17 -> 7260.6238 | AA18: =+AA14-AA17 -> 8170.1798 | AB18: =+AB14-AB17 -> 9152.4578 | ... AE18: =+AE14-AE17 -> 12196.756
C19: Other Income | D19: 108 | E19: 82 | F19: 124 | G19: =+V19-F19-E19-D19 -> 109 | H19: 28 | I19: 17 | J19: 46 | K19: =+W19-J19-I19-H19 -> 29 | L19: 88 | M19: 25 | U19: 885 | V19: 423 | W19: 120 | X19: =+(M19+L19)*2 -> 226 | Y19: 100 | Z19: 100 | AA19: 100 | AB19: 100 | AC19: 100 | AD19: 100 | AE19: 100
C20: Pension | D20: 491 | E20: 490 | F20: 491 | G20: =+V20-F20-E20-D20 -> 472 | H20: 480 | I20: 474 | J20: 468 | K20: =+W20-J20-I20-H20 -> 467 | L20: 444 | M20: 447 | U20: 902 | V20: 1944 | W20: 1889 | X20: =+(M20+L20)*2 -> 1782 | Y20: =+X20*0.98 -> 1746.36 | Z20: =+Y20*0.98 -> 1711.4328 | AA20: =+Z20*0.98 -> 1677.2041 | AB20: =+AA20*0.98 -> 1643.6601 | AC20: =+AB20*0.98 -> 1610.7869 | AD20: =+AC20*0.98 -> 1578.5711 | AE20: =+AD20*0.98 -> 1546.9997
C21: Interest Expense | D21: 346 | E21: 342 | F21: 358 | G21: =+V21-F21-E21-D21 -> 925 | H21: 318 | I21: 329 | J21: 311 | K21: =+W21-J21-I21-H21 -> 318 | L21: 315 | M21: 333 | U21: 1366 | V21: =1322+649 -> 1971 | W21: 1276 | X21: =+(M21+L21)*2 -> 1296 | Y21: =+X21*1.01 -> 1308.96 | Z21: =+Y21*1.01 -> 1322.0496 | AA21: =+Z21*1.01 -> 1335.2701 | AB21: =+AA21*1.01 -> 1348.6228 | AC21: =+AB21*1.01 -> 1362.109 | AD21: =+AC21*1.01 -> 1375.7301 | AE21: =+AD21*1.01 -> 1389.4874
C22: Pretax | D22: =+D18+D19+D20-D21 -> 1158 | E22: =+E18+E19+E20-E21 -> 1430 | F22: =+F18+F19+F20-F21 -> 1476 | G22: =+G18+G19+G20-G21 -> 867 | H22: =+H18+H19+H20-H21 -> 1242 | I22: =+I18+I19+I20-I21 -> 1498 | J22: =+J18+J19+J20-J21 -> 1637 | K22: =+K18+K19+K20-K21 -> 1650 | ... M22: =+M18+M19+M20-M21 -> 1572 | U22: =+U18+U19+U20-U21 -> 831 | V22: =+V18+V19+V20-V21 -> 4931 | W22: =+W18+W19+W20-W21 -> 6027 | X22: =+X18+X19+X20-X21 -> 6706 | Y22: =+Y18+Y19+Y20-Y21 -> 6991.5672 | Z22: =+Z18+Z19+Z20-Z21 -> 7750.007 | AA22: =+AA18+AA19+AA20-AA21 -> 8612.1138 | AB22: =+AB18+AB19+AB20-AB21 -> 9547.495 | ... AE22: =+AE18+AE19+AE20-AE21 -> 12454.268
C23: Taxes | D23: 345 | E23: 342 | F23: 3 | G23: =+V23-F23-E23-D23 -> 96 | H23: 116 | I23: 160 | J23: 242 | K23: =+W23-J23-I23-H23 -> 182 | L23: 300 | M23: 213 | U23: 575 | V23: 786 | W23: 700 | X23: =+(M23+L23)*2 -> 1026 | Y23: =+Y22*0.15 -> 1048.7351 | Z23: =+Z22*0.15 -> 1162.501 | AA23: =+AA22*0.15 -> 1291.8171 | AB23: =+AB22*0.15 -> 1432.1243 | AC23: =+AC22*0.15 -> 1594.3677 | AD23: =+AD22*0.15 -> 1727.016 | AE23: =+AE22*0.15 -> 1868.1402
C24: Net Income | D24: =+D22-D23 -> 813 | E24: =+E22-E23 -> 1088 | F24: =+F22-F23 -> 1473 | G24: =+G22-G23 -> 771 | H24: =+H22-H23 -> 1126 | I24: =+I22-I23 -> 1338 | J24: =+J22-J23 -> 1395 | K24: =+K22-K23 -> 1468 | ... M24: =+M22-M23 -> 1359 | U24: =+U22-U23 -> 256 | V24: =+V22-V23 -> 4145 | W24: =+W22-W23 -> 5327 | X24: =+X22-X23 -> 5680 | Y24: =+Y22-Y23 -> 5942.8321 | Z24: =+Z22-Z23 -> 6587.5059 | AA24: =+AA22-AA23 -> 7320.2968 | AB24: =+AB22-AB23 -> 8115.3708 | ... AE24: =+AE22-AE23 -> 10586.128 | AF24: =+AE24*(1+TR) -> 10903.712 | AG24: =+AF24*(1+TR) -> 11230.823 | AH24: =+AG24*(1+TR) -> 11567.748 | AI24: =+AH24*(1+TR) -> 11914.78 | AJ24: =+AI24*(1+TR) -> 12272.223 | AK24: =+AJ24*(1+TR) -> 12640.39 | AL24: =+AK24*(1+TR) -> 13019.602 | AM24: =+AL24*(1+TR) -> 13410.19 | ... EL24: =+EK24*(1+TR) -> 281623.62
C25: Shares | D25: 1514.1 | E25: 1513.5 | F25: 1505.9 | G25: =+V25 -> 1508.5 | H25: 1497.9 | I25: 1489.6 | J25: 1479.3 | K25: =+W25 -> 1485.9 | L25: 1461.142 | M25: 1455.5149 | U25: 1357.8 | V25: 1508.5 | W25: 1485.9 | X25: =+W25 -> 1485.9 | Y25: =+X25+0 -> 1485.9 | Z25: =+Y25+0 -> 1485.9 | AA25: =+Z25+0 -> 1485.9 | AB25: =+AA25+0 -> 1485.9 | AC25: =+AB25+0 -> 1485.9 | AD25: =+AC25+0 -> 1485.9 | AE25: =+AD25+0 -> 1485.9
C26: EPS | D26: =+D24/D25 -> 0.53695265 | E26: =+E24/E25 -> 0.71886356 | F26: =+F24/F25 -> 0.9781526 | G26: =+G24/G25 -> 0.51110375 | H26: =+H24/H25 -> 0.75171907 | I26: =+I24/I25 -> 0.89822771 | J26: =+J24/J25 -> 0.94301359 | K26: =+K24/K25 -> 0.98795343 | ... M26: =+M24/M25 -> 0.93369017 | U26: =+U24/U25 -> 0.18854029 | V26: =+V24/V25 -> 2.7477627 | W26: =+W24/W25 -> 3.5850326 | X26: =+X24/X25 -> 3.8225991 | Y26: =+Y24/Y25 -> 3.9994832 | Z26: =+Z24/Z25 -> 4.4333441 | AA26: =+AA24/AA25 -> 4.926507 | AB26: =+AB24/AB25 -> 5.4615861 | ... AE26: =+AE24/AE25 -> 7.1243877
C28: Gross Margin | D28: =+D14/D10 -> 0.17795554 | E28: =+E14/E10 -> 0.20308564 | F28: =+F14/F10 -> 0.19268488 | G28: =+G14/G10 -> 0.2011265 | H28: =+H14/H10 -> 0.20081446 | I28: =+I14/I10 -> 0.21196518 | J28: =+J14/J10 -> 0.20571058 | K28: =+K14/K10 -> 0.19714807 | U28: =+U14/U10 -> 0.15075901 | V28: =+V14/V10 -> 0.19399578 | W28: =+W14/W10 -> 0.20377494 | X28: =+X14/X10 -> 0.20732359 | Y28: =+Y14/Y10 -> 0.20461463 | Z28: =+Z14/Z10 -> 0.20509144 | AA28: =+AA14/AA10 -> 0.20557237 | AB28: =+AB14/AB10 -> 0.20605739 | ... AE28: =+AE14/AE10 -> 0.20704657
C29: Product Margin | D29: =+(D8-D11)/D8 -> 0.14489026 | E29: =+(E8-E11)/E8 -> 0.17916085 | F29: =+(F8-F11)/F8 -> 0.16503122 | G29: =+(G8-G11)/G8 -> 0.17318265 | H29: =+(H8-H11)/H8 -> 0.17214635 | I29: =+(I8-I11)/I8 -> 0.18094306 | J29: =+(J8-J11)/J8 -> 0.17740671 | K29: =+(K8-K11)/K8 -> 0.16715838 | U29: =+(U8-U11)/U8 -> 0.11962418 | V29: =+(V8-V11)/V8 -> 0.16592247 | W29: =+(W8-W11)/W8 -> 0.17422646 | X29: =+(X8-X11)/X8 -> 0.16829529 | Y29: =+(Y8-Y11)/Y8 -> 0.17 | Z29: =+(Z8-Z11)/Z8 -> 0.17 | AA29: =+(AA8-AA11)/AA8 -> 0.17 | AB29: =+(AB8-AB11)/AB8 -> 0.17 | ... AE29: =+(AE8-AE11)/AE8 -> 0.17
C30: Serice Margin | D30: =+(D9-D12)/D9 -> 0.28547533 | E30: =+(E9-E12)/E9 -> 0.28181573 | F30: =+(F9-F12)/F9 -> 0.2805255 | G30: =+(G9-G12)/G9 -> 0.29381966 | H30: =+(H9-H12)/H9 -> 0.28905034 | I30: =+(I9-I12)/I9 -> 0.30571992 | J30: =+(J9-J12)/J9 -> 0.29177592 | K30: =+(K9-K12)/K9 -> 0.29647283 | U30: =+(U9-U12)/U9 -> 0.25241182 | V30: =+(V9-V12)/V9 -> 0.2854875 | W30: =+(W9-W12)/W9 -> 0.29581007 | X30: =+(X9-X12)/X9 -> 0.31690065 | Y30: =+(Y9-Y12)/Y9 -> 0.3 | Z30: =+(Z9-Z12)/Z9 -> 0.3 | AA30: =+(AA9-AA12)/AA9 -> 0.3 | AB30: =+(AB9-AB12)/AB9 -> 0.3 | ... AE30: =+(AE9-AE12)/AE9 -> 0.3
C31: Net Margin | D31: =+D24/D10 -> 0.05330798 | E31: =+E24/E10 -> 0.068513854 | F31: =+F24/F10 -> 0.090853019 | G31: =+G24/G10 -> 0.04523586 | H31: =+H24/H10 -> 0.071646729 | I31: =+I24/I10 -> 0.082015447 | J31: =+J24/J10 -> 0.08229603 | K31: =+K24/K10 -> 0.081136351 | U31: =+U24/U10 -> 0.0045240073 | V31: =+V24/V10 -> 0.064375349 | W31: =+W24/W10 -> 0.079419745 | X31: =+X24/X10 -> 0.079934701 | Y31: =+Y24/Y10 -> 0.078510524 | Z31: =+Z24/Z10 -> 0.081690806 | AA31: =+AA24/AA10 -> 0.085205709 | AB31: =+AB24/AB10 -> 0.088655576 | ... AE31: =+AE24/AE10 -> 0.097915879
C33: Product Margin | D33: =+(D8-D11)/D8 -> 0.14489026 | E33: =+(E8-E11)/E8 -> 0.17916085 | F33: =+(F8-F11)/F8 -> 0.16503122 | G33: =+(G8-G11)/G8 -> 0.17318265 | H33: =+(H8-H11)/H8 -> 0.17214635 | I33: =+(I8-I11)/I8 -> 0.18094306 | J33: =+(J8-J11)/J8 -> 0.17740671 | K33: =+(K8-K11)/K8 -> 0.16715838 | ... M33: =+(M8-M11)/M8 -> 0.17314145 | V33: =+(V8-V11)/V8 -> 0.16592247 | W33: =+(W8-W11)/W8 -> 0.17422646 | X33: =+(X8-X11)/X8 -> 0.16829529 | Y33: =+(Y8-Y11)/Y8 -> 0.17 | Z33: =+(Z8-Z11)/Z8 -> 0.17 | AA33: =+(AA8-AA11)/AA8 -> 0.17 | AB33: =+(AB8-AB11)/AB8 -> 0.17 | AC33: =+(AC8-AC11)/AC8 -> 0.17 | ... AE33: =+(AE8-AE11)/AE8 -> 0.17
C34: Service Margin | D34: =+(D9-D12)/D9 -> 0.28547533 | E34: =+(E9-E12)/E9 -> 0.28181573 | F34: =+(F9-F12)/F9 -> 0.2805255 | G34: =+(G9-G12)/G9 -> 0.29381966 | H34: =+(H9-H12)/H9 -> 0.28905034 | I34: =+(I9-I12)/I9 -> 0.30571992 | J34: =+(J9-J12)/J9 -> 0.29177592 | K34: =+(K9-K12)/K9 -> 0.29647283 | ... M34: =+(M9-M12)/M9 -> 0.30077488 | V34: =+(V9-V12)/V9 -> 0.2854875 | W34: =+(W9-W12)/W9 -> 0.29581007 | X34: =+(X9-X12)/X9 -> 0.31690065 | Y34: =+(Y9-Y12)/Y9 -> 0.3 | Z34: =+(Z9-Z12)/Z9 -> 0.3 | AA34: =+(AA9-AA12)/AA9 -> 0.3 | AB34: =+(AB9-AB12)/AB9 -> 0.3 | AC34: =+(AC9-AC12)/AC9 -> 0.3 | ... AE34: =+(AE9-AE12)/AE9 -> 0.3 | AG34: Discount | AH34: 0.1
C35: Net Income Y/Y | V35: =+V24/U24 -1 -> 15.191406 | W35: =+W24/V24 -1 -> 0.28516285 | X35: =+X24/W24 -1 -> 0.066266191 | Y35: =+Y24/X24 -1 -> 0.046273261 | Z35: =+Z24/Y24 -1 -> 0.10847923 | AA35: =+AA24/Z24 -1 -> 0.11123949 | AB35: =+AB24/AA24 -1 -> 0.10861226 | AC35: =+AC24/AB24 -1 -> 0.11328865 | ... AE35: =+AE24/AD24 -1 -> 0.081715614 | AG35: Terminal | AH35: 0.03
AG36: NPV | AH36: =NPV(AH34,X24:EW24) -> 112741.03
C37: CFFO | D37: 723 | E37: =2049-D37 -> 1326 | F37: =3981-E37-D37 -> 1932 | H37: 476 | I37: =1762-H37 -> 1286 | J37: =2540-I37-H37 -> 778 | U37: 4334 | V37: 7142 | W37: 7168 | AG37: Price | AH37: =+AH36/AE25 -> 75.8739
C38: CapEx | D38: 387 | E38: =747-D38 -> 360 | F38: =1180-E38-D38 -> 433 | H38: 439 | I38: =918-H38 -> 479 | J38: =1433-I38-H38 -> 515 | U38: 1795 | V38: 2134 | W38: 2288
C39: FCF | D39: =+D37-D38 -> 336 | E39: =+E37-E38 -> 966 | F39: =+F37-F38 -> 1499 | G39: =+G37-G38 -> 0 | H39: =+H37-H38 -> 37 | I39: =+I37-I38 -> 807 | J39: =+J37-J38 -> 263 | K39: =+K37-K38 -> 0 | U39: =+U37-U38 -> 2539 | V39: =+V37-V38 -> 5008 | W39: =+W37-W38 -> 4880
C41: Cash | M41: 5391 | V41: 7832 | W41: 6220
C42: AR | M42: 9903 | V42: 9661 | W42: 9108
C43: PP&E | M43: 15000 | V43: 14972 | W43: 15170
C44: Debt | M44: =1554+32723 -> 34277 | V44: =134+24+31327 -> 31485 | W44: =625+595+30694 -> 31914
C45: NAV | M45: =+M41+M43+M42-M44 -> -3983 | V45: =+V41+V43+V42-V44 -> 980 | W45: =+W41+W43+W42-W44 -> -1416
